Workbook

Sheet samples
A1: project | B1: smell | C1: package | D1: class | E1: fqn | F1: prompt_file | G1: context_size | H1: designite | I1: gpt | J1: deepseek | K1: qwen
A2: javaparser | B2: Insufficient Modularization | C2: com.github.javaparser.symbolsolver.javaparsermodel.contexts | D2: AnonymousClassDeclarationContext | E2: =C2&"."&D2 -> com.github.javaparser.symbolsolver.javaparsermodel.contexts.AnonymousClassDeclarationContext | F2: data/processed/prompts/insufficient_modularization/javaparser/com_github_javaparser_symbolsolver_javaparsermodel_contexts_AnonymousClassDeclarationContext.txt | G2: 495 | H2: 0 | I2: =VLOOKUP(E2,gpt!E2:F5422,2,0) -> 1 | J2: =VLOOKUP(E2,deepseek!E2:F5422,2,0) -> 0 | K2: =VLOOKUP(E2,qwen!E2:F5422,2,0) -> 0
A3: byte-buddy | B3: Insufficient Modularization | C3: net.bytebuddy.dynamic.DynamicType | D3: Initial | E3: =C3&"."&D3 -> net.bytebuddy.dynamic.DynamicType.Initial | F3: data/processed/prompts/insufficient_modularization/byte-buddy/net_bytebuddy_dynamic_DynamicType_Initial.txt | G3: 348 | H3: 0 | I3: =VLOOKUP(E3,gpt!E3:F5423,2,0) -> 0 | J3: =VLOOKUP(E3,deepseek!E3:F5423,2,0) -> 1 | K3: =VLOOKUP(E3,qwen!E3:F5423,2,0) -> 0
A4: javaparser | B4: Insufficient Modularization | C4: com.packageName | D4: ClassInPackage | E4: =C4&"."&D4 -> com.packageName.ClassInPackage | F4: data/processed/prompts/insufficient_modularization/javaparser/com_packageName_ClassInPackage.txt | G4: 338 | H4: 0 | I4: =VLOOKUP(E4,gpt!E4:F5424,2,0) -> 0 | J4: =VLOOKUP(E4,deepseek!E4:F5424,2,0) -> 0 | K4: =VLOOKUP(E4,qwen!E4:F5424,2,0) -> 0
A5: byte-buddy | B5: Insufficient Modularization | C5: net.bytebuddy.description.type.TypeList | D5: Empty | E5: =C5&"."&D5 -> net.bytebuddy.description.type.TypeList.Empty | F5: data/processed/prompts/insufficient_modularization/byte-buddy/net_bytebuddy_description_type_TypeList_Empty.txt | G5: 368 | H5: 0 | I5: =VLOOKUP(E5,gpt!E5:F5425,2,0) -> 0 | J5: =VLOOKUP(E5,deepseek!E5:F5425,2,0) -> 0 | K5: =VLOOKUP(E5,qwen!E5:F5425,2,0) -> 0
A6: byte-buddy | B6: Insufficient Modularization | C6: net.bytebuddy.description.type.RecordComponentDescription | D6: InDefinedShape | E6: =C6&"."&D6 -> net.bytebuddy.description.type.RecordComponentDescription.InDefinedShape | F6: data/processed/prompts/insufficient_modularization/byte-buddy/net_bytebuddy_description_type_RecordComponentDescription_InDefinedShape.txt | G6: 355 | H6: 0 | I6: =VLOOKUP(E6,gpt!E6:F5426,2,0) -> 0 | J6: =VLOOKUP(E6,deepseek!E6:F5426,2,0) -> 0 | K6: =VLOOKUP(E6,qwen!E6:F5426,2,0) -> 0
A7: commons-io | B7: Insufficient Modularization | C7: org.apache.commons.io | D7: CloseableURLConnection | E7: =C7&"."&D7 -> org.apache.commons.io.CloseableURLConnection | F7: data/processed/prompts/insufficient_modularization/commons-io/org_apache_commons_io_CloseableURLConnection.txt | G7: 327 | H7: 1 | I7: =VLOOKUP(E7,gpt!E7:F5427,2,0) -> 1 | J7: =VLOOKUP(E7,deepseek!E7:F5427,2,0) -> 1 | K7: =VLOOKUP(E7,qwen!E7:F5427,2,0) -> 1
A8: byte-buddy | B8: Insufficient Modularization | C8: net.bytebuddy.implementation.bind.MethodDelegationBinder | D8: Compound | E8: =C8&"."&D8 -> net.bytebuddy.implementation.bind.MethodDelegationBinder.Compound | F8: data/processed/prompts/insufficient_modularization/byte-buddy/net_bytebuddy_implementation_bind_MethodDelegationBinder_Compound.txt | G8: 350 | H8: 0 | I8: =VLOOKUP(E8,gpt!E8:F5428,2,0) -> 0 | J8: =VLOOKUP(E8,deepseek!E8:F5428,2,0) -> 1 | K8: =VLOOKUP(E8,qwen!E8:F5428,2,0) -> 0
A9: zxing | B9: Insufficient Modularization | C9: com.google.zxing | D9: ResultPointCallback | E9: =C9&"."&D9 -> com.google.zxing.ResultPointCallback | F9: data/processed/prompts/insufficient_modularization/zxing/com_google_zxing_ResultPointCallback.txt | G9: 330 | H9: 0 | I9: =VLOOKUP(E9,gpt!E9:F5429,2,0) -> 0 | J9: =VLOOKUP(E9,deepseek!E9:F5429,2,0) -> 0 | K9: =VLOOKUP(E9,qwen!E9:F5429,2,0) -> 0
A10: byte-buddy | B10: Insufficient Modularization | C10: net.bytebuddy.dynamic.scaffold.inline | D10: MethodRebaseResolver | E10: =C10&"."&D10 -> net.bytebuddy.dynamic.scaffold.inline.MethodRebaseResolver | F10: data/processed/prompts/insufficient_modularization/byte-buddy/net_bytebuddy_dynamic_scaffold_inline_MethodRebaseResolver.txt | G10: 478 | H10: 0 | I10: =VLOOKUP(E10,gpt!E10:F5430,2,0) -> 1 | J10: =VLOOKUP(E10,deepseek!E10:F5430,2,0) -> 1 | K10: =VLOOKUP(E10,qwen!E10:F5430,2,0) -> 1
A11: byte-buddy | B11: Insufficient Modularization | C11: net.bytebuddy.implementation.bytecode.assign.primitive.PrimitiveUnboxingDelegate | D11: UnboxingResponsible | E11: =C11&"."&D11 -> net.bytebuddy.implementation.bytecode.assign.primitive.PrimitiveUnboxingDelegate.UnboxingResponsible | F11: data/processed/prompts/insufficient_modularization/byte-buddy/net_bytebuddy_implementation_bytecode_assign_primitive_PrimitiveUnboxingDelegate_UnboxingResponsible.txt | G11: 370 | H11: 0 | I11: =VLOOKUP(E11,gpt!E11:F5431,2,0) -> 0 | J11: =VLOOKUP(E11,deepseek!E11:F5431,2,0) -> 0 | K11: =VLOOKUP(E11,qwen!E11:F5431,2,0) -> 0
A12: jitwatch | B12: Insufficient Modularization | C12: (default package) | D12: ElisionTest | E12: =C12&"."&D12 -> (default package).ElisionTest | F12: data/processed/prompts/insufficient_modularization/jitwatch/(default package)_ElisionTest.txt | G12: 320 | H12: 0 | I12: =VLOOKUP(E12,gpt!E12:F5432,2,0) -> 0 | J12: =VLOOKUP(E12,deepseek!E12:F5432,2,0) -> 0 | K12: =VLOOKUP(E12,qwen!E12:F5432,2,0) -> 0
A13: byte-buddy | B13: Insufficient Modularization | C13: net.bytebuddy | D13: NamingStrategy | E13: =C13&"."&D13 -> net.bytebuddy.NamingStrategy | F13: data/processed/prompts/insufficient_modularization/byte-buddy/net_bytebuddy_NamingStrategy.txt | G13: 387 | H13: 0 | I13: =VLOOKUP(E13,gpt!E13:F5433,2,0) -> 1 | J13: =VLOOKUP(E13,deepseek!E13:F5433,2,0) -> 1 | K13: =VLOOKUP(E13,qwen!E13:F5433,2,0) -> 0
... A33: byte-buddy | B33: Insufficient Modularization | C33: net.bytebuddy.description.method.ParameterList | D33: OfMethod | E33: =C33&"."&D33 -> net.bytebuddy.description.method.ParameterList.OfMethod | F33: data/processed/prompts/insufficient_modularization/byte-buddy/net_bytebuddy_description_method_ParameterList_OfMethod.txt | G33: 343 | H33: 0 | I33: =VLOOKUP(E33,gpt!E33:F5453,2,0) -> 0 | J33: =VLOOKUP(E33,deepseek!E33:F5453,2,0) -> 0 | K33: =VLOOKUP(E33,qwen!E33:F5453,2,0) -> 0
A34: byte-buddy | B34: Insufficient Modularization | C34: net.bytebuddy.benchmark.jmh.generated.SuperClassInvocationBenchmark.benchmarkByteBuddyWithPrefix | D34: jmhTest | E34: =C34&"."&D34 -> net.bytebuddy.benchmark.jmh.generated.SuperClassInvocationBenchmark.benchmarkByteBuddyWithPrefix.jmhTest | F34: data/processed/prompts/insufficient_modularization/byte-buddy/net_bytebuddy_benchmark_jmh_generated_SuperClassInvocationBenchmark_benchmarkByteBuddyWithPrefix_jmhTest.txt | G34: 4528 | H34: 0 | I34: =VLOOKUP(E34,gpt!E34:F5454,2,0) -> 1 | J34: =VLOOKUP(E34,deepseek!E34:F5454,2,0) -> 1 | K34: 0
A35: zxing | B35: Insufficient Modularization | C35: com.google.zxing.oned.rss.expanded.decoders | D35: AI013103decoder | E35: =C35&"."&D35 -> com.google.zxing.oned.rss.expanded.decoders.AI013103decoder | F35: data/processed/prompts/insufficient_modularization/zxing/com_google_zxing_oned_rss_expanded_decoders_AI013103decoder.txt | G35: 350 | H35: 0 | I35: =VLOOKUP(E35,gpt!E35:F5455,2,0) -> 0 | J35: =VLOOKUP(E35,deepseek!E35:F5455,2,0) -> 0 | K35: =VLOOKUP(E35,qwen!E35:F5455,2,0) -> 0
A36: javaparser | B36: Insufficient Modularization | C36: com.github.javaparser.symbolsolver.utils | D36: FileUtils | E36: =C36&"."&D36 -> com.github.javaparser.symbolsolver.utils.FileUtils | F36: data/processed/prompts/insufficient_modularization/javaparser/com_github_javaparser_symbolsolver_utils_FileUtils.txt | G36: 340 | H36: 0 | I36: =VLOOKUP(E36,gpt!E36:F5456,2,0) -> 0 | J36: =VLOOKUP(E36,deepseek!E36:F5456,2,0) -> 0 | K36: =VLOOKUP(E36,qwen!E36:F5456,2,0) -> 0
A37: commons-lang | B37: Insufficient Modularization | C37: org.apache.commons.lang3.event | D37: EventListenerSupport | E37: =C37&"."&D37 -> org.apache.commons.lang3.event.EventListenerSupport | F37: data/processed/prompts/insufficient_modularization/commons-lang/org_apache_commons_lang3_event_EventListenerSupport.txt | G37: 342 | H37: 0 | I37: =VLOOKUP(E37,gpt!E37:F5457,2,0) -> 0 | J37: =VLOOKUP(E37,deepseek!E37:F5457,2,0) -> 1 | K37: =VLOOKUP(E37,qwen!E37:F5457,2,0) -> 0
A38: commons-lang | B38: Insufficient Modularization | C38: org.apache.commons.lang3.Strings | D38: CsStrings | E38: =C38&"."&D38 -> org.apache.commons.lang3.Strings.CsStrings | F38: data/processed/prompts/insufficient_modularization/commons-lang/org_apache_commons_lang3_Strings_CsStrings.txt | G38: 326 | H38: 0 | I38: =VLOOKUP(E38,gpt!E38:F5458,2,0) -> 0 | J38: =VLOOKUP(E38,deepseek!E38:F5458,2,0) -> 0 | K38: =VLOOKUP(E38,qwen!E38:F5458,2,0) -> 0
A39: zxing | B39: Insufficient Modularization | C39: com.google.zxing.web | D39: OutputUtils | E39: =C39&"."&D39 -> com.google.zxing.web.OutputUtils | F39: data/processed/prompts/insufficient_modularization/zxing/com_google_zxing_web_OutputUtils.txt | G39: 331 | H39: 0 | I39: =VLOOKUP(E39,gpt!E39:F5459,2,0) -> 1 | J39: =VLOOKUP(E39,deepseek!E39:F5459,2,0) -> 0 | K39: =VLOOKUP(E39,qwen!E39:F5459,2,0) -> 0
A40: byte-buddy | B40: Insufficient Modularization | C40: net.bytebuddy.asm.MemberSubstitution | D40: Dispatcher | E40: =C40&"."&D40 -> net.bytebuddy.asm.MemberSubstitution.Dispatcher | F40: data/processed/prompts/insufficient_modularization/byte-buddy/net_bytebuddy_asm_MemberSubstitution_Dispatcher.txt | G40: 394 | H40: 0 | I40: =VLOOKUP(E40,gpt!E40:F5460,2,0) -> 1 | J40: =VLOOKUP(E40,deepseek!E40:F5460,2,0) -> 1 | K40: =VLOOKUP(E40,qwen!E40:F5460,2,0) -> 1
A41: byte-buddy | B41: Insufficient Modularization | C41: net.bytebuddy.implementation.bytecode.member | D41: Invokedynamic | E41: =C41&"."&D41 -> net.bytebuddy.implementation.bytecode.member.Invokedynamic | F41: data/processed/prompts/insufficient_modularization/byte-buddy/net_bytebuddy_implementation_bytecode_member_Invokedynamic.txt | G41: 392 | H41: 0 | I41: =VLOOKUP(E41,gpt!E41:F5461,2,0) -> 0 | J41: =VLOOKUP(E41,deepseek!E41:F5461,2,0) -> 0 | K41: =VLOOKUP(E41,qwen!E41:F5461,2,0) -> 0
A42: byte-buddy | B42: Insufficient Modularization | C42: net.bytebuddy.description.method.ParameterList | D42: OfLegacyVmMethod | E42: =C42&"."&D42 -> net.bytebuddy.description.method.ParameterList.OfLegacyVmMethod | F42: data/processed/prompts/insufficient_modularization/byte-buddy/net_bytebuddy_description_method_ParameterList_OfLegacyVmMethod.txt | G42: 354 | H42: 0 | I42: =VLOOKUP(E42,gpt!E42:F5462,2,0) -> 0 | J42: =VLOOKUP(E42,deepseek!E42:F5462,2,0) -> 0 | K42: =VLOOKUP(E42,qwen!E42:F5462,2,0) -> 0
A43: javaparser | B43: Insufficient Modularization | C43: com.github.javaparser.utils | D43: ParserCollectionStrategy | E43: =C43&"."&D43 -> com.github.javaparser.utils.ParserCollectionStrategy | F43: data/processed/prompts/insufficient_modularization/javaparser/com_github_javaparser_utils_ParserCollectionStrategy.txt | G43: 357 | H43: 0 | I43: =VLOOKUP(E43,gpt!E43:F5463,2,0) -> 0 | J43: =VLOOKUP(E43,deepseek!E43:F5463,2,0) -> 0 | K43: =VLOOKUP(E43,qwen!E43:F5463,2,0) -> 0
A44: byte-buddy | B44: Insufficient Modularization | C44: org.gradle.api.tasks | D44: PathSensitivity | E44: =C44&"."&D44 -> org.gradle.api.tasks.PathSensitivity | F44: data/processed/prompts/insufficient_modularization/byte-buddy/org_gradle_api_tasks_PathSensitivity.txt | G44: 335 | H44: 0 | I44: =VLOOKUP(E44,gpt!E44:F5464,2,0) -> 0 | J44: =VLOOKUP(E44,deepseek!E44:F5464,2,0) -> 0 | K44: =VLOOKUP(E44,qwen!E44:F5464,2,0) -> 0
A45: commons-io | B45: Insufficient Modularization | C45: org.apache.commons.io.input | D45: UncheckedFilterReader | E45: =C45&"."&D45 -> org.apache.commons.io.input.UncheckedFilterReader | F45: data/processed/prompts/insufficient_modularization/commons-io/org_apache_commons_io_input_UncheckedFilterReader.txt | G45: 347 | H45: 0 | I45: =VLOOKUP(E45,gpt!E45:F5465,2,0) -> 0 | J45: =VLOOKUP(E45,deepseek!E45:F5465,2,0) -> 0 | K45: =VLOOKUP(E45,qwen!E45:F5465,2,0) -> 0
A46: byte-buddy | B46: Insufficient Modularization | C46: net.bytebuddy.implementation.auxiliary.TypeProxy | D46: MethodCall | E46: =C46&"."&D46 -> net.bytebuddy.implementation.auxiliary.TypeProxy.MethodCall | F46: data/processed/prompts/insufficient_modularization/byte-buddy/net_bytebuddy_implementation_auxiliary_TypeProxy_MethodCall.txt | G46: 398 | H46: 0 | I46: =VLOOKUP(E46,gpt!E46:F5466,2,0) -> 0 | J46: =VLOOKUP(E46,deepseek!E46:F5466,2,0) -> 1 | K46: =VLOOKUP(E46,qwen!E46:F5466,2,0) -> 0
... A135: byte-buddy | B135: Insufficient Modularization | C135: net.bytebuddy.utility | D135: StreamDrainer | E135: =C135&"."&D135 -> net.bytebuddy.utility.StreamDrainer | F135: data/processed/prompts/insufficient_modularization/byte-buddy/net_bytebuddy_utility_StreamDrainer.txt | G135: 347 | H135: 0 | I135: =VLOOKUP(E135,gpt!E135:F5555,2,0) -> 1 | J135: =VLOOKUP(E135,deepseek!E135:F5555,2,0) -> 0 | K135: =VLOOKUP(E135,qwen!E135:F5555,2,0) -> 0
A136: javaparser | B136: Insufficient Modularization | C136: com.github.javaparser.javasymbolsolver.javassist.symbols.main.jar | D136: InterfaceUserOwnJar | E136: =C136&"."&D136 -> com.github.javaparser.javasymbolsolver.javassist.symbols.main.jar.InterfaceUserOwnJar | F136: data/processed/prompts/insufficient_modularization/javaparser/com_github_javaparser_javasymbolsolver_javassist_symbols_main_jar_InterfaceUserOwnJar.txt | G136: 369 | H136: 0 | I136: =VLOOKUP(E136,gpt!E136:F5556,2,0) -> 0 | J136: =VLOOKUP(E136,deepseek!E136:F5556,2,0) -> 0 | K136: 0
A137: byte-buddy | B137: Insufficient Modularization | C137: net.bytebuddy.build.maven | D137: Initialization | E137: =C137&"."&D137 -> net.bytebuddy.build.maven.Initialization | F137: data/processed/prompts/insufficient_modularization/byte-buddy/net_bytebuddy_build_maven_Initialization.txt | G137: 348 | H137: 0 | I137: =VLOOKUP(E137,gpt!E137:F5557,2,0) -> 0 | J137: =VLOOKUP(E137,deepseek!E137:F5557,2,0) -> 0 | K137: =VLOOKUP(E137,qwen!E137:F5557,2,0) -> 0
A138: byte-buddy | B138: Insufficient Modularization | C138: net.bytebuddy.implementation.attribute | D138: AnnotationValueFilter | E138: =C138&"."&D138 -> net.bytebuddy.implementation.attribute.AnnotationValueFilter | F138: data/processed/prompts/insufficient_modularization/byte-buddy/net_bytebuddy_implementation_attribute_AnnotationValueFilter.txt | G138: 353 | H138: 0 | I138: =VLOOKUP(E138,gpt!E138:F5558,2,0) -> 0 | J138: =VLOOKUP(E138,deepseek!E138:F5558,2,0) -> 1 | K138: =VLOOKUP(E138,qwen!E138:F5558,2,0) -> 0
A139: javaparser | B139: Insufficient Modularization | C139: main.Clazz | D139: MyEnum | E139: =C139&"."&D139 -> main.Clazz.MyEnum | F139: data/processed/prompts/insufficient_modularization/javaparser/main_Clazz_MyEnum.txt | G139: 336 | H139: 0 | I139: =VLOOKUP(E139,gpt!E139:F5559,2,0) -> 0 | J139: =VLOOKUP(E139,deepseek!E139:F5559,2,0) -> 0 | K139: =VLOOKUP(E139,qwen!E139:F5559,2,0) -> 0
A140: byte-buddy | B140: Insufficient Modularization | C140: net.bytebuddy.asm.MemberSubstitution | D140: Sort | E140: =C140&"."&D140 -> net.bytebuddy.asm.MemberSubstitution.Sort | F140: data/processed/prompts/insufficient_modularization/byte-buddy/net_bytebuddy_asm_MemberSubstitution_Sort.txt | G140: 349 | H140: 0 | I140: =VLOOKUP(E140,gpt!E140:F5560,2,0) -> 1 | J140: =VLOOKUP(E140,deepseek!E140:F5560,2,0) -> 1 | K140: =VLOOKUP(E140,qwen!E140:F5560,2,0) -> 0
A141: byte-buddy | B141: Insufficient Modularization | C141: net.bytebuddy.implementation.Implementation | D141: FrameGeneration | E141: =C141&"."&D141 -> net.bytebuddy.implementation.Implementation.FrameGeneration | F141: data/processed/prompts/insufficient_modularization/byte-buddy/net_bytebuddy_implementation_Implementation_FrameGeneration.txt | G141: 332 | H141: 0 | I141: =VLOOKUP(E141,gpt!E141:F5561,2,0) -> 0 | J141: =VLOOKUP(E141,deepseek!E141:F5561,2,0) -> 1 | K141: =VLOOKUP(E141,qwen!E141:F5561,2,0) -> 0
A142: javaparser | B142: Insufficient Modularization | C142: com.github.javaparser.printer.lexicalpreservation.ReshuffledDiffElementExtractor | D142: MatchClassification | E142: =C142&"."&D142 -> com.github.javaparser.printer.lexicalpreservation.ReshuffledDiffElementExtractor.MatchClassification | F142: data/processed/prompts/insufficient_modularization/javaparser/com_github_javaparser_printer_lexicalpreservation_ReshuffledDiffElementExtractor_MatchClassification.txt | G142: 354 | H142: 0 | I142: =VLOOKUP(E142,gpt!E142:F5562,2,0) -> 0 | J142: =VLOOKUP(E142,deepseek!E142:F5562,2,0) -> 0 | K142: =VLOOKUP(E142,qwen!E142:F5562,2,0) -> 0
A143: byte-buddy | B143: Insufficient Modularization | C143: net.bytebuddy.build.HashCodeAndEqualsPlugin | D143: Sort | E143: =C143&"."&D143 -> net.bytebuddy.build.HashCodeAndEqualsPlugin.Sort | F143: data/processed/prompts/insufficient_modularization/byte-buddy/net_bytebuddy_build_HashCodeAndEqualsPlugin_Sort.txt | G143: 337 | H143: 0 | I143: =VLOOKUP(E143,gpt!E143:F5563,2,0) -> 0 | J143: =VLOOKUP(E143,deepseek!E143:F5563,2,0) -> 0 | K143: =VLOOKUP(E143,qwen!E143:F5563,2,0) -> 0
A144: jitwatch | B144: Insufficient Modularization | C144: org.adoptopenjdk.jitwatch.ui.Dialogs | D144: Dialog | E144: =C144&"."&D144 -> org.adoptopenjdk.jitwatch.ui.Dialogs.Dialog | F144: data/processed/prompts/insufficient_modularization/jitwatch/org_adoptopenjdk_jitwatch_ui_Dialogs_Dialog.txt | G144: 332 | H144: 0 | I144: =VLOOKUP(E144,gpt!E144:F5564,2,0) -> 0 | J144: =VLOOKUP(E144,deepseek!E144:F5564,2,0) -> 0 | K144: =VLOOKUP(E144,qwen!E144:F5564,2,0) -> 0
A145: commons-lang | B145: Insufficient Modularization | C145: org.apache.commons.lang3.exception | D145: CloneFailedException | E145: =C145&"."&D145 -> org.apache.commons.lang3.exception.CloneFailedException | F145: data/processed/prompts/insufficient_modularization/commons-lang/org_apache_commons_lang3_exception_CloneFailedException.txt | G145: 330 | H145: 0 | I145: =VLOOKUP(E145,gpt!E145:F5565,2,0) -> 0 | J145: =VLOOKUP(E145,deepseek!E145:F5565,2,0) -> 0 | K145: =VLOOKUP(E145,qwen!E145:F5565,2,0) -> 0
A146: javaparser | B146: Insufficient Modularization | C146: com.github.javaparser.metamodel | D146: TypeParameterMetaModel | E146: =C146&"."&D146 -> com.github.javaparser.metamodel.TypeParameterMetaModel | F146: data/processed/prompts/insufficient_modularization/javaparser/com_github_javaparser_metamodel_TypeParameterMetaModel.txt | G146: 347 | H146: 0 | I146: =VLOOKUP(E146,gpt!E146:F5566,2,0) -> 0 | J146: =VLOOKUP(E146,deepseek!E146:F5566,2,0) -> 0 | K146: =VLOOKUP(E146,qwen!E146:F5566,2,0) -> 0
A147: zxing | B147: Insufficient Modularization | C147: com.google.zxing.datamatrix.decoder | D147: DataBlock | E147: =C147&"."&D147 -> com.google.zxing.datamatrix.decoder.DataBlock | F147: data/processed/prompts/insufficient_modularization/zxing/com_google_zxing_datamatrix_decoder_DataBlock.txt | G147: 339 | H147: 0 | I147: =VLOOKUP(E147,gpt!E147:F5567,2,0) -> 0 | J147: =VLOOKUP(E147,deepseek!E147:F5567,2,0) -> 0 | K147: =VLOOKUP(E147,qwen!E147:F5567,2,0) -> 0
A148: byte-buddy | B148: Insufficient Modularization | C148: net.bytebuddy.description.modifier | D148: Ownership | E148: =C148&"."&D148 -> net.bytebuddy.description.modifier.Ownership | F148: data/processed/prompts/insufficient_modularization/byte-buddy/net_bytebuddy_description_modifier_Ownership.txt | G148: 342 | H148: 0 | I148: =VLOOKUP(E148,gpt!E148:F5568,2,0) -> 1 | J148: =VLOOKUP(E148,deepseek!E148:F5568,2,0) -> 1 | K148: =VLOOKUP(E148,qwen!E148:F5568,2,0) -> 0
... A161: commons-lang | B161: Insufficient Modularization | C161: org.apache.commons.lang3.time | D161: FastDateFormat | E161: =C161&"."&D161 -> org.apache.commons.lang3.time.FastDateFormat | F161: data/processed/prompts/insufficient_modularization/commons-lang/org_apache_commons_lang3_time_FastDateFormat.txt | G161: 365 | H161: 1 | I161: =VLOOKUP(E161,gpt!E161:F5581,2,0) -> 1 | J161: =VLOOKUP(E161,deepseek!E161:F5581,2,0) -> 1 | K161: =VLOOKUP(E161,qwen!E161:F5581,2,0) -> 1
A162: javaparser | B162: Insufficient Modularization | C162: com.github.javaparser.ast.validator.language.level.validations | D162: Java16Validator | E162: =C162&"."&D162 -> com.github.javaparser.ast.validator.language.level.validations.Java16Validator | F162: data/processed/prompts/insufficient_modularization/javaparser/com_github_javaparser_ast_validator_language_level_validations_Java16Validator.txt | G162: 348 | H162: 0 | I162: =VLOOKUP(E162,gpt!E162:F5582,2,0) -> 0 | J162: =VLOOKUP(E162,deepseek!E162:F5582,2,0) -> 0 | K162: 0
A163: zxing | B163: Insufficient Modularization | C163: com.google.zxing.client.result | D163: AddressBookDoCoMoResultParser | E163: =C163&"."&D163 -> com.google.zxing.client.result.AddressBookDoCoMoResultParser | F163: data/processed/prompts/insufficient_modularization/zxing/com_google_zxing_client_result_AddressBookDoCoMoResultParser.txt | G163: 353 | H163: 0 | I163: =VLOOKUP(E163,gpt!E163:F5583,2,0) -> 0 | J163: =VLOOKUP(E163,deepseek!E163:F5583,2,0) -> 0 | K163: =VLOOKUP(E163,qwen!E163:F5583,2,0) -> 0
A164: zxing | B164: Insufficient Modularization | C164: com.google.zxing.common | D164: BitMatrix | E164: =C164&"."&D164 -> com.google.zxing.common.BitMatrix | F164: data/processed/prompts/insufficient_modularization/zxing/com_google_zxing_common_BitMatrix.txt | G164: 335 | H164: 1 | I164: =VLOOKUP(E164,gpt!E164:F5584,2,0) -> 1 | J164: =VLOOKUP(E164,deepseek!E164:F5584,2,0) -> 1 | K164: =VLOOKUP(E164,qwen!E164:F5584,2,0) -> 1
A165: byte-buddy | B165: Insufficient Modularization | C165: net.bytebuddy.asm.MemberSubstitution | D165: Source | E165: =C165&"."&D165 -> net.bytebuddy.asm.MemberSubstitution.Source | F165: data/processed/prompts/insufficient_modularization/byte-buddy/net_bytebuddy_asm_MemberSubstitution_Source.txt | G165: 378 | H165: 0 | I165: =VLOOKUP(E165,gpt!E165:F5585,2,0) -> 1 | J165: =VLOOKUP(E165,deepseek!E165:F5585,2,0) -> 1 | K165: =VLOOKUP(E165,qwen!E165:F5585,2,0) -> 0
A166: javaparser | B166: Insufficient Modularization | C166: com.github.javaparser.utils.Log | D166: StandardOutStandardErrorAdapter | E166: =C166&"."&D166 -> com.github.javaparser.utils.Log.StandardOutStandardErrorAdapter | F166: data/processed/prompts/insufficient_modularization/javaparser/com_github_javaparser_utils_Log_StandardOutStandardErrorAdapter.txt | G166: 336 | H166: 0 | I166: =VLOOKUP(E166,gpt!E166:F5586,2,0) -> 0 | J166: =VLOOKUP(E166,deepseek!E166:F5586,2,0) -> 0 | K166: =VLOOKUP(E166,qwen!E166:F5586,2,0) -> 0
A167: gson | B167: Insufficient Modularization | C167: com.google.gson.internal | D167: TroubleshootingGuide | E167: =C167&"."&D167 -> com.google.gson.internal.TroubleshootingGuide | F167: data/processed/prompts/insufficient_modularization/gson/com_google_gson_internal_TroubleshootingGuide.txt | G167: 328 | H167: 0 | I167: =VLOOKUP(E167,gpt!E167:F5587,2,0) -> 0 | J167: =VLOOKUP(E167,deepseek!E167:F5587,2,0) -> 0 | K167: =VLOOKUP(E167,qwen!E167:F5587,2,0) -> 0
A168: byte-buddy | B168: Insufficient Modularization | C168: net.bytebuddy.pool.TypePool | D168: ForType | E168: =C168&"."&D168 -> net.bytebuddy.pool.TypePool.ForType | F168: data/processed/prompts/insufficient_modularization/byte-buddy/net_bytebuddy_pool_TypePool_ForType.txt | G168: 351 | H168: 0 | I168: =VLOOKUP(E168,gpt!E168:F5588,2,0) -> 0 | J168: =VLOOKUP(E168,deepseek!E168:F5588,2,0) -> 0 | K168: =VLOOKUP(E168,qwen!E168:F5588,2,0) -> 0
A169: jitwatch | B169: Insufficient Modularization | C169: org.adoptopenjdk.jitwatch.process.compiler | D169: CompilerJava | E169: =C169&"."&D169 -> org.adoptopenjdk.jitwatch.process.compiler.CompilerJava | F169: data/processed/prompts/insufficient_modularization/jitwatch/org_adoptopenjdk_jitwatch_process_compiler_CompilerJava.txt | G169: 347 | H169: 0 | I169: =VLOOKUP(E169,gpt!E169:F5589,2,0) -> 0 | J169: =VLOOKUP(E169,deepseek!E169:F5589,2,0) -> 0 | K169: =VLOOKUP(E169,qwen!E169:F5589,2,0) -> 0
A170: javaparser | B170: Insufficient Modularization | C170: (default package).InnerClassDotExpressions | D170: InnerClass | E170: =C170&"."&D170 -> (default package).InnerClassDotExpressions.InnerClass | F170: data/processed/prompts/insufficient_modularization/javaparser/(default package)_InnerClassDotExpressions_InnerClass.txt | G170: 339 | H170: 0 | I170: =VLOOKUP(E170,gpt!E170:F5590,2,0) -> 0 | J170: =VLOOKUP(E170,deepseek!E170:F5590,2,0) -> 0 | K170: =VLOOKUP(E170,qwen!E170:F5590,2,0) -> 0
A171: zxing | B171: Insufficient Modularization | C171: com.google.zxing.client.j2se | D171: MatrixToImageConfig | E171: =C171&"."&D171 -> com.google.zxing.client.j2se.MatrixToImageConfig | F171: data/processed/prompts/insufficient_modularization/zxing/com_google_zxing_client_j2se_MatrixToImageConfig.txt | G171: 334 | H171: 0 | I171: =VLOOKUP(E171,gpt!E171:F5591,2,0) -> 0 | J171: =VLOOKUP(E171,deepseek!E171:F5591,2,0) -> 0 | K171: =VLOOKUP(E171,qwen!E171:F5591,2,0) -> 0
A172: byte-buddy | B172: Insufficient Modularization | C172: net.bytebuddy.description.type | D172: PackageDescription | E172: =C172&"."&D172 -> net.bytebuddy.description.type.PackageDescription | F172: data/processed/prompts/insufficient_modularization/byte-buddy/net_bytebuddy_description_type_PackageDescription.txt | G172: 357 | H172: 0 | I172: =VLOOKUP(E172,gpt!E172:F5592,2,0) -> 0 | J172: =VLOOKUP(E172,deepseek!E172:F5592,2,0) -> 0 | K172: =VLOOKUP(E172,qwen!E172:F5592,2,0) -> 0
A173: byte-buddy | B173: Insufficient Modularization | C173: net.bytebuddy.agent.VirtualMachine | D173: SecurityAttributes | E173: =C173&"."&D173 -> net.bytebuddy.agent.VirtualMachine.SecurityAttributes | F173: data/processed/prompts/insufficient_modularization/byte-buddy/net_bytebuddy_agent_VirtualMachine_SecurityAttributes.txt | G173: 332 | H173: 0 | I173: =VLOOKUP(E173,gpt!E173:F5593,2,0) -> 0 | J173: =VLOOKUP(E173,deepseek!E173:F5593,2,0) -> 0 | K173: =VLOOKUP(E173,qwen!E173:F5593,2,0) -> 0
A174: byte-buddy | B174: Insufficient Modularization | C174: net.bytebuddy.dynamic.scaffold.TypeWriter | D174: ForImplicitRecordComponent | E174: =C174&"."&D174 -> net.bytebuddy.dynamic.scaffold.TypeWriter.ForImplicitRecordComponent | F174: data/processed/prompts/insufficient_modularization/byte-buddy/net_bytebuddy_dynamic_scaffold_TypeWriter_ForImplicitRecordComponent.txt | G174: 381 | H174: 0 | I174: =VLOOKUP(E174,gpt!E174:F5594,2,0) -> 0 | J174: =VLOOKUP(E174,deepseek!E174:F5594,2,0) -> 0 | K174: =VLOOKUP(E174,qwen!E174:F5594,2,0) -> 0
... A179: zxing | B179: Insufficient Modularization | C179: com.google.zxing.client.android.HttpHelper | D179: ContentType | E179: =C179&"."&D179 -> com.google.zxing.client.android.HttpHelper.ContentType | F179: data/processed/prompts/insufficient_modularization/zxing/com_google_zxing_client_android_HttpHelper_ContentType.txt | G179: 326 | H179: 0 | I179: =VLOOKUP(E179,gpt!E179:F5599,2,0) -> 0 | J179: =VLOOKUP(E179,deepseek!E179:F5599,2,0) -> 0 | K179: =VLOOKUP(E179,qwen!E179:F5599,2,0) -> 0
A180: byte-buddy | B180: Insufficient Modularization | C180: net.bytebuddy.benchmark.jmh.generated.ClassByImplementationBenchmark.benchmarkJavassist | D180: jmhTest | E180: =C180&"."&D180 -> net.bytebuddy.benchmark.jmh.generated.ClassByImplementationBenchmark.benchmarkJavassist.jmhTest | F180: data/processed/prompts/insufficient_modularization/byte-buddy/net_bytebuddy_benchmark_jmh_generated_ClassByImplementationBenchmark_benchmarkJavassist_jmhTest.txt | G180: 4465 | H180: 0 | I180: =VLOOKUP(E180,gpt!E180:F5600,2,0) -> 1 | J180: =VLOOKUP(E180,deepseek!E180:F5600,2,0) -> 1 | K180: 0
A181: jitwatch | B181: Insufficient Modularization | C181: org.adoptopenjdk.jitwatch.parser.zing | D181: ZingLine | E181: =C181&"."&D181 -> org.adoptopenjdk.jitwatch.parser.zing.ZingLine | F181: data/processed/prompts/insufficient_modularization/jitwatch/org_adoptopenjdk_jitwatch_parser_zing_ZingLine.txt | G181: 418 | H181: 1 | I181: =VLOOKUP(E181,gpt!E181:F5601,2,0) -> 1 | J181: =VLOOKUP(E181,deepseek!E181:F5601,2,0) -> 1 | K181: =VLOOKUP(E181,qwen!E181:F5601,2,0) -> 1
A182: commons-io | B182: Insufficient Modularization | C182: org.apache.commons.io | D182: ByteOrderParser | E182: =C182&"."&D182 -> org.apache.commons.io.ByteOrderParser | F182: data/processed/prompts/insufficient_modularization/commons-io/org_apache_commons_io_ByteOrderParser.txt | G182: 326 | H182: 0 | I182: =VLOOKUP(E182,gpt!E182:F5602,2,0) -> 0 | J182: =VLOOKUP(E182,deepseek!E182:F5602,2,0) -> 0 | K182: =VLOOKUP(E182,qwen!E182:F5602,2,0) -> 0
A183: byte-buddy | B183: Insufficient Modularization | C183: net.bytebuddy.NamingStrategy | D183: PrefixingRandom | E183: =C183&"."&D183 -> net.bytebuddy.NamingStrategy.PrefixingRandom | F183: data/processed/prompts/insufficient_modularization/byte-buddy/net_bytebuddy_NamingStrategy_PrefixingRandom.txt | G183: 349 | H183: 0 | I183: =VLOOKUP(E183,gpt!E183:F5603,2,0) -> 0 | J183: =VLOOKUP(E183,deepseek!E183:F5603,2,0) -> 0 | K183: =VLOOKUP(E183,qwen!E183:F5603,2,0) -> 0
A184: byte-buddy | B184: Insufficient Modularization | C184: net.bytebuddy.dynamic.scaffold.TypeWriter | D184: BridgeTarget | E184: =C184&"."&D184 -> net.bytebuddy.dynamic.scaffold.TypeWriter.BridgeTarget | F184: data/processed/prompts/insufficient_modularization/byte-buddy/net_bytebuddy_dynamic_scaffold_TypeWriter_BridgeTarget.txt | G184: 381 | H184: 0 | I184: =VLOOKUP(E184,gpt!E184:F5604,2,0) -> 1 | J184: =VLOOKUP(E184,deepseek!E184:F5604,2,0) -> 1 | K184: =VLOOKUP(E184,qwen!E184:F5604,2,0) -> 0
A185: byte-buddy | B185: Insufficient Modularization | C185: net.bytebuddy.build.AccessControllerPlugin | D185: Initializer | E185: =C185&"."&D185 -> net.bytebuddy.build.AccessControllerPlugin.Initializer | F185: data/processed/prompts/insufficient_modularization/byte-buddy/net_bytebuddy_build_AccessControllerPlugin_Initializer.txt | G185: 361 | H185: 0 | I185: =VLOOKUP(E185,gpt!E185:F5605,2,0) -> 0 | J185: =VLOOKUP(E185,deepseek!E185:F5605,2,0) -> 1 | K185: =VLOOKUP(E185,qwen!E185:F5605,2,0) -> 0
A186: jsoup | B186: Insufficient Modularization | C186: org.jsoup.nodes | D186: Entities | E186: =C186&"."&D186 -> org.jsoup.nodes.Entities | F186: data/processed/prompts/insufficient_modularization/jsoup/org_jsoup_nodes_Entities.txt | G186: 388 | H186: 0 | I186: =VLOOKUP(E186,gpt!E186:F5606,2,0) -> 1 | J186: =VLOOKUP(E186,deepseek!E186:F5606,2,0) -> 1 | K186: =VLOOKUP(E186,qwen!E186:F5606,2,0) -> 1
A187: byte-buddy | B187: Insufficient Modularization | C187: net.bytebuddy.implementation.LoadedTypeInitializer | D187: Compound | E187: =C187&"."&D187 -> net.bytebuddy.implementation.LoadedTypeInitializer.Compound | F187: data/processed/prompts/insufficient_modularization/byte-buddy/net_bytebuddy_implementation_LoadedTypeInitializer_Compound.txt | G187: 345 | H187: 0 | I187: =VLOOKUP(E187,gpt!E187:F5607,2,0) -> 0 | J187: =VLOOKUP(E187,deepseek!E187:F5607,2,0) -> 0 | K187: =VLOOKUP(E187,qwen!E187:F5607,2,0) -> 0
A188: byte-buddy | B188: Insufficient Modularization | C188: net.bytebuddy.implementation.bind.MethodDelegationBinder | D188: MethodInvoker | E188: =C188&"."&D188 -> net.bytebuddy.implementation.bind.MethodDelegationBinder.MethodInvoker | F188: data/processed/prompts/insufficient_modularization/byte-buddy/net_bytebuddy_implementation_bind_MethodDelegationBinder_MethodInvoker.txt | G188: 359 | H188: 0 | I188: =VLOOKUP(E188,gpt!E188:F5608,2,0) -> 0 | J188: =VLOOKUP(E188,deepseek!E188:F5608,2,0) -> 1 | K188: =VLOOKUP(E188,qwen!E188:F5608,2,0) -> 0
A189: javaparser | B189: Insufficient Modularization | C189: com.github.javaparser.serialization | D189: JavaParserJsonSerializer | E189: =C189&"."&D189 -> com.github.javaparser.serialization.JavaParserJsonSerializer | F189: data/processed/prompts/insufficient_modularization/javaparser/com_github_javaparser_serialization_JavaParserJsonSerializer.txt | G189: 464 | H189: 0 | I189: =VLOOKUP(E189,gpt!E189:F5609,2,0) -> 0 | J189: =VLOOKUP(E189,deepseek!E189:F5609,2,0) -> 1 | K189: =VLOOKUP(E189,qwen!E189:F5609,2,0) -> 1
A190: byte-buddy | B190: Insufficient Modularization | C190: net.bytebuddy.pool.TypePool | D190: LazyAnnotationDescription | E190: =C190&"."&D190 -> net.bytebuddy.pool.TypePool.LazyAnnotationDescription | F190: data/processed/prompts/insufficient_modularization/byte-buddy/net_bytebuddy_pool_TypePool_LazyAnnotationDescription.txt | G190: 386 | H190: 0 | I190: =VLOOKUP(E190,gpt!E190:F5610,2,0) -> 1 | J190: =VLOOKUP(E190,deepseek!E190:F5610,2,0) -> 1 | K190: =VLOOKUP(E190,qwen!E190:F5610,2,0) -> 0
A191: byte-buddy | B191: Insufficient Modularization | C191: net.bytebuddy.matcher | D191: FieldTypeMatcher | E191: =C191&"."&D191 -> net.bytebuddy.matcher.FieldTypeMatcher | F191: data/processed/prompts/insufficient_modularization/byte-buddy/net_bytebuddy_matcher_FieldTypeMatcher.txt | G191: 359 | H191: 0 | I191: =VLOOKUP(E191,gpt!E191:F5611,2,0) -> 0 | J191: =VLOOKUP(E191,deepseek!E191:F5611,2,0) -> 0 | K191: =VLOOKUP(E191,qwen!E191:F5611,2,0) -> 0
A192: jsoup | B192: Insufficient Modularization | C192: org.jsoup.select.Evaluator | D192: IsNthLastOfType | E192: =C192&"."&D192 -> org.jsoup.select.Evaluator.IsNthLastOfType | F192: data/processed/prompts/insufficient_modularization/jsoup/org_jsoup_select_Evaluator_IsNthLastOfType.txt | G192: 323 | H192: 0 | I192: =VLOOKUP(E192,gpt!E192:F5612,2,0) -> 0 | J192: =VLOOKUP(E192,deepseek!E192:F5612,2,0) -> 0 | K192: =VLOOKUP(E192,qwen!E192:F5612,2,0) -> 0
... A217: byte-buddy | B217: Insufficient Modularization | C217: net.bytebuddy.implementation.MethodDelegation | D217: ForStaticMethod | E217: =C217&"."&D217 -> net.bytebuddy.implementation.MethodDelegation.ForStaticMethod | F217: data/processed/prompts/insufficient_modularization/byte-buddy/net_bytebuddy_implementation_MethodDelegation_ForStaticMethod.txt | G217: 358 | H217: 0 | I217: =VLOOKUP(E217,gpt!E217:F5637,2,0) -> 0 | J217: =VLOOKUP(E217,deepseek!E217:F5637,2,0) -> 1 | K217: =VLOOKUP(E217,qwen!E217:F5637,2,0) -> 0
A218: byte-buddy | B218: Insufficient Modularization | C218: net.bytebuddy.benchmark.jmh.generated.SuperClassInvocationBenchmark.benchmarkByteBuddyWithProxy | D218: jmhTest | E218: =C218&"."&D218 -> net.bytebuddy.benchmark.jmh.generated.SuperClassInvocationBenchmark.benchmarkByteBuddyWithProxy.jmhTest | F218: data/processed/prompts/insufficient_modularization/byte-buddy/net_bytebuddy_benchmark_jmh_generated_SuperClassInvocationBenchmark_benchmarkByteBuddyWithProxy_jmhTest.txt | G218: 4528 | H218: 0 | I218: =VLOOKUP(E218,gpt!E218:F5638,2,0) -> 1 | J218: =VLOOKUP(E218,deepseek!E218:F5638,2,0) -> 1 | K218: 0
A219: byte-buddy | B219: Insufficient Modularization | C219: net.bytebuddy.implementation.bytecode | D219: TypeCreation | E219: =C219&"."&D219 -> net.bytebuddy.implementation.bytecode.TypeCreation | F219: data/processed/prompts/insufficient_modularization/byte-buddy/net_bytebuddy_implementation_bytecode_TypeCreation.txt | G219: 376 | H219: 0 | I219: =VLOOKUP(E219,gpt!E219:F5639,2,0) -> 0 | J219: =VLOOKUP(E219,deepseek!E219:F5639,2,0) -> 0 | K219: =VLOOKUP(E219,qwen!E219:F5639,2,0) -> 0
A220: byte-buddy | B220: Insufficient Modularization | C220: net.bytebuddy.dynamic.scaffold.TypeWriter | D220: ForInterface | E220: =C220&"."&D220 -> net.bytebuddy.dynamic.scaffold.TypeWriter.ForInterface | F220: data/processed/prompts/insufficient_modularization/byte-buddy/net_bytebuddy_dynamic_scaffold_TypeWriter_ForInterface.txt | G220: 344 | H220: 0 | I220: =VLOOKUP(E220,gpt!E220:F5640,2,0) -> 1 | J220: =VLOOKUP(E220,deepseek!E220:F5640,2,0) -> 0 | K220: =VLOOKUP(E220,qwen!E220:F5640,2,0) -> 0
A221: javaparser | B221: Insufficient Modularization | C221: com.github.javaparser.symbolsolver | D221: SourceFileInfoExtractor | E221: =C221&"."&D221 -> com.github.javaparser.symbolsolver.SourceFileInfoExtractor | F221: data/processed/prompts/insufficient_modularization/javaparser/com_github_javaparser_symbolsolver_SourceFileInfoExtractor.txt | G221: 498 | H221: 0 | I221: =VLOOKUP(E221,gpt!E221:F5641,2,0) -> 1 | J221: =VLOOKUP(E221,deepseek!E221:F5641,2,0) -> 1 | K221: =VLOOKUP(E221,qwen!E221:F5641,2,0) -> 1
A222: javaparser | B222: Insufficient Modularization | C222: issue241.TypeWithMemberType | D222: MemberInterface | E222: =C222&"."&D222 -> issue241.TypeWithMemberType.MemberInterface | F222: data/processed/prompts/insufficient_modularization/javaparser/issue241_TypeWithMemberType_MemberInterface.txt | G222: 336 | H222: 0 | I222: =VLOOKUP(E222,gpt!E222:F5642,2,0) -> 0 | J222: =VLOOKUP(E222,deepseek!E222:F5642,2,0) -> 0 | K222: =VLOOKUP(E222,qwen!E222:F5642,2,0) -> 0
A223: jimfs | B223: Insufficient Modularization | C223: com.google.common.jimfs | D223: RegularFile | E223: =C223&"."&D223 -> com.google.common.jimfs.RegularFile | F223: data/processed/prompts/insufficient_modularization/jimfs/com_google_common_jimfs_RegularFile.txt | G223: 372 | H223: 1 | I223: =VLOOKUP(E223,gpt!E223:F5643,2,0) -> 1 | J223: =VLOOKUP(E223,deepseek!E223:F5643,2,0) -> 1 | K223: =VLOOKUP(E223,qwen!E223:F5643,2,0) -> 1
A224: javaparser | B224: Insufficient Modularization | C224: com.github.javaparser.utils.VisitorList | D224: EqualsHashcodeOverridingFacade | E224: =C224&"."&D224 -> com.github.javaparser.utils.VisitorList.EqualsHashcodeOverridingFacade | F224: data/processed/prompts/insufficient_modularization/javaparser/com_github_javaparser_utils_VisitorList_EqualsHashcodeOverridingFacade.txt | G224: 349 | H224: 0 | I224: =VLOOKUP(E224,gpt!E224:F5644,2,0) -> 0 | J224: =VLOOKUP(E224,deepseek!E224:F5644,2,0) -> 0 | K224: =VLOOKUP(E224,qwen!E224:F5644,2,0) -> 0
A225: byte-buddy | B225: Insufficient Modularization | C225: net.bytebuddy.implementation.InvokeDynamic | D225: ForInterceptedMethodParameters | E225: =C225&"."&D225 -> net.bytebuddy.implementation.InvokeDynamic.ForInterceptedMethodParameters | F225: data/processed/prompts/insufficient_modularization/byte-buddy/net_bytebuddy_implementation_InvokeDynamic_ForInterceptedMethodParameters.txt | G225: 347 | H225: 0 | I225: =VLOOKUP(E225,gpt!E225:F5645,2,0) -> 0 | J225: =VLOOKUP(E225,deepseek!E225:F5645,2,0) -> 0 | K225: =VLOOKUP(E225,qwen!E225:F5645,2,0) -> 0
A226: byte-buddy | B226: Insufficient Modularization | C226: net.bytebuddy.dynamic.scaffold.MethodGraph | D226: NodeList | E226: =C226&"."&D226 -> net.bytebuddy.dynamic.scaffold.MethodGraph.NodeList | F226: data/processed/prompts/insufficient_modularization/byte-buddy/net_bytebuddy_dynamic_scaffold_MethodGraph_NodeList.txt | G226: 353 | H226: 0 | I226: =VLOOKUP(E226,gpt!E226:F5646,2,0) -> 0 | J226: =VLOOKUP(E226,deepseek!E226:F5646,2,0) -> 0 | K226: =VLOOKUP(E226,qwen!E226:F5646,2,0) -> 0
A227: byte-buddy | B227: Insufficient Modularization | C227: net.bytebuddy.pool.TypePool | D227: ForAnnotationValue | E227: =C227&"."&D227 -> net.bytebuddy.pool.TypePool.ForAnnotationValue | F227: data/processed/prompts/insufficient_modularization/byte-buddy/net_bytebuddy_pool_TypePool_ForAnnotationValue.txt | G227: 359 | H227: 0 | I227: =VLOOKUP(E227,gpt!E227:F5647,2,0) -> 0 | J227: =VLOOKUP(E227,deepseek!E227:F5647,2,0) -> 0 | K227: =VLOOKUP(E227,qwen!E227:F5647,2,0) -> 0
A228: jitwatch | B228: Insufficient Modularization | C228: (default package) | D228: TestInner | E228: =C228&"."&D228 -> (default package).TestInner | F228: data/processed/prompts/insufficient_modularization/jitwatch/(default package)_TestInner.txt | G228: 317 | H228: 0 | I228: =VLOOKUP(E228,gpt!E228:F5648,2,0) -> 0 | J228: =VLOOKUP(E228,deepseek!E228:F5648,2,0) -> 0 | K228: =VLOOKUP(E228,qwen!E228:F5648,2,0) -> 0
A229: commons-io | B229: Insufficient Modularization | C229: org.apache.commons.io.input | D229: BrokenReader | E229: =C229&"."&D229 -> org.apache.commons.io.input.BrokenReader | F229: data/processed/prompts/insufficient_modularization/commons-io/org_apache_commons_io_input_BrokenReader.txt | G229: 338 | H229: 0 | I229: =VLOOKUP(E229,gpt!E229:F5649,2,0) -> 0 | J229: =VLOOKUP(E229,deepseek!E229:F5649,2,0) -> 1 | K229: =VLOOKUP(E229,qwen!E229:F5649,2,0) -> 0
A230: jitwatch | B230: Insufficient Modularization | C230: org.adoptopenjdk.jitwatch.ui.main | D230: ClassMemberList | E230: =C230&"."&D230 -> org.adoptopenjdk.jitwatch.ui.main.ClassMemberList | F230: data/processed/prompts/insufficient_modularization/jitwatch/org_adoptopenjdk_jitwatch_ui_main_ClassMemberList.txt | G230: 444 | H230: 0 | I230: =VLOOKUP(E230,gpt!E230:F5650,2,0) -> 0 | J230: =VLOOKUP(E230,deepseek!E230:F5650,2,0) -> 1 | K230: =VLOOKUP(E230,qwen!E230:F5650,2,0) -> 1
... A239: javaparser | B239: Insufficient Modularization | C239: com.github.javaparser.JavaToken | D239: Kind | E239: =C239&"."&D239 -> com.github.javaparser.JavaToken.Kind | F239: data/processed/prompts/insufficient_modularization/javaparser/com_github_javaparser_JavaToken_Kind.txt | G239: 332 | H239: 0 | I239: =VLOOKUP(E239,gpt!E239:F5659,2,0) -> 1 | J239: =VLOOKUP(E239,deepseek!E239:F5659,2,0) -> 0 | K239: =VLOOKUP(E239,qwen!E239:F5659,2,0) -> 0
A240: byte-buddy | B240: Insufficient Modularization | C240: net.bytebuddy.agent.VirtualMachine | D240: UsingStat | E240: =C240&"."&D240 -> net.bytebuddy.agent.VirtualMachine.UsingStat | F240: data/processed/prompts/insufficient_modularization/byte-buddy/net_bytebuddy_agent_VirtualMachine_UsingStat.txt | G240: 333 | H240: 0 | I240: 0 | J240: 0 | K240: 0
A241: commons-io | B241: Insufficient Modularization | C241: org.apache.commons.io.input | D241: CountingInputStream | E241: =C241&"."&D241 -> org.apache.commons.io.input.CountingInputStream | F241: data/processed/prompts/insufficient_modularization/commons-io/org_apache_commons_io_input_CountingInputStream.txt | G241: 341 | H241: 0 | I241: =VLOOKUP(E241,gpt!E241:F5661,2,0) -> 0 | J241: =VLOOKUP(E241,deepseek!E241:F5661,2,0) -> 0 | K241: =VLOOKUP(E241,qwen!E241:F5661,2,0) -> 0
A242: byte-buddy | B242: Insufficient Modularization | C242: net.bytebuddy.description.type.TypeDescription | D242: LazyInterfaceList | E242: =C242&"."&D242 -> net.bytebuddy.description.type.TypeDescription.LazyInterfaceList | F242: data/processed/prompts/insufficient_modularization/byte-buddy/net_bytebuddy_description_type_TypeDescription_LazyInterfaceList.txt | G242: 344 | H242: 0 | I242: =VLOOKUP(E242,gpt!E242:F5662,2,0) -> 0 | J242: =VLOOKUP(E242,deepseek!E242:F5662,2,0) -> 1 | K242: =VLOOKUP(E242,qwen!E242:F5662,2,0) -> 0
A243: jimfs | B243: Insufficient Modularization | C243: com.google.common.jimfs | D243: JimfsInputStream | E243: =C243&"."&D243 -> com.google.common.jimfs.JimfsInputStream | F243: data/processed/prompts/insufficient_modularization/jimfs/com_google_common_jimfs_JimfsInputStream.txt | G243: 352 | H243: 0 | I243: =VLOOKUP(E243,gpt!E243:F5663,2,0) -> 0 | J243: =VLOOKUP(E243,deepseek!E243:F5663,2,0) -> 0 | K243: =VLOOKUP(E243,qwen!E243:F5663,2,0) -> 0
A244: javaparser | B244: Insufficient Modularization | C244: com.github.javaparser.symbolsolver.cache | D244: NoCache | E244: =C244&"."&D244 -> com.github.javaparser.symbolsolver.cache.NoCache | F244: data/processed/prompts/insufficient_modularization/javaparser/com_github_javaparser_symbolsolver_cache_NoCache.txt | G244: 351 | H244: 0 | I244: =VLOOKUP(E244,gpt!E244:F5664,2,0) -> 0 | J244: =VLOOKUP(E244,deepseek!E244:F5664,2,0) -> 0 | K244: =VLOOKUP(E244,qwen!E244:F5664,2,0) -> 0
A245: javaparser | B245: Insufficient Modularization | C245: com.github.javaparser.symbolsolver.core.resolution | D245: MethodUsageResolutionCapability | E245: =C245&"."&D245 -> com.github.javaparser.symbolsolver.core.resolution.MethodUsageResolutionCapability | F245: data/processed/prompts/insufficient_modularization/javaparser/com_github_javaparser_symbolsolver_core_resolution_MethodUsageResolutionCapability.txt | G245: 357 | H245: 0 | I245: =VLOOKUP(E245,gpt!E245:F5665,2,0) -> 0 | J245: =VLOOKUP(E245,deepseek!E245:F5665,2,0) -> 0 | K245: =VLOOKUP(E245,qwen!E245:F5665,2,0) -> 0
A246: commons-io | B246: Insufficient Modularization | C246: org.apache.commons.io | D246: FilenameUtils | E246: =C246&"."&D246 -> org.apache.commons.io.FilenameUtils | F246: data/processed/prompts/insufficient_modularization/commons-io/org_apache_commons_io_FilenameUtils.txt | G246: 343 | H246: 1 | I246: =VLOOKUP(E246,gpt!E246:F5666,2,0) -> 1 | J246: =VLOOKUP(E246,deepseek!E246:F5666,2,0) -> 1 | K246: =VLOOKUP(E246,qwen!E246:F5666,2,0) -> 1
A247: byte-buddy | B247: Insufficient Modularization | C247: net.bytebuddy.implementation.bind.annotation.Binder | D247: FieldSetter | E247: =C247&"."&D247 -> net.bytebuddy.implementation.bind.annotation.Binder.FieldSetter | F247: data/processed/prompts/insufficient_modularization/byte-buddy/net_bytebuddy_implementation_bind_annotation_Binder_FieldSetter.txt | G247: 412 | H247: 0 | I247: =VLOOKUP(E247,gpt!E247:F5667,2,0) -> 0 | J247: =VLOOKUP(E247,deepseek!E247:F5667,2,0) -> 0 | K247: =VLOOKUP(E247,qwen!E247:F5667,2,0) -> 0
A248: byte-buddy | B248: Insufficient Modularization | C248: net.bytebuddy.description.type.TypeDescription | D248: ForTypeVariable | E248: =C248&"."&D248 -> net.bytebuddy.description.type.TypeDescription.ForTypeVariable | F248: data/processed/prompts/insufficient_modularization/byte-buddy/net_bytebuddy_description_type_TypeDescription_ForTypeVariable.txt | G248: 345 | H248: 0 | I248: =VLOOKUP(E248,gpt!E248:F5668,2,0) -> 0 | J248: =VLOOKUP(E248,deepseek!E248:F5668,2,0) -> 0 | K248: =VLOOKUP(E248,qwen!E248:F5668,2,0) -> 0
A249: javaparser | B249: Insufficient Modularization | C249: com.github.javaparser.metamodel | D249: YieldStmtMetaModel | E249: =C249&"."&D249 -> com.github.javaparser.metamodel.YieldStmtMetaModel | F249: data/processed/prompts/insufficient_modularization/javaparser/com_github_javaparser_metamodel_YieldStmtMetaModel.txt | G249: 347 | H249: 0 | I249: =VLOOKUP(E249,gpt!E249:F5669,2,0) -> 0 | J249: =VLOOKUP(E249,deepseek!E249:F5669,2,0) -> 0 | K249: =VLOOKUP(E249,qwen!E249:F5669,2,0) -> 0
A250: zxing | B250: Insufficient Modularization | C250: com.google.zxing.datamatrix.decoder.Version | D250: ECBlocks | E250: =C250&"."&D250 -> com.google.zxing.datamatrix.decoder.Version.ECBlocks | F250: data/processed/prompts/insufficient_modularization/zxing/com_google_zxing_datamatrix_decoder_Version_ECBlocks.txt | G250: 332 | H250: 0 | I250: =VLOOKUP(E250,gpt!E250:F5670,2,0) -> 0 | J250: =VLOOKUP(E250,deepseek!E250:F5670,2,0) -> 0 | K250: =VLOOKUP(E250,qwen!E250:F5670,2,0) -> 0
A251: javaparser | B251: Insufficient Modularization | C251: com.github.javaparser.resolution | D251: Resolvable | E251: =C251&"."&D251 -> com.github.javaparser.resolution.Resolvable | F251: data/processed/prompts/insufficient_modularization/javaparser/com_github_javaparser_resolution_Resolvable.txt | G251: 333 | H251: 0 | I251: =VLOOKUP(E251,gpt!E251:F5671,2,0) -> 0 | J251: =VLOOKUP(E251,deepseek!E251:F5671,2,0) -> 0 | K251: =VLOOKUP(E251,qwen!E251:F5671,2,0) -> 0
A252: byte-buddy | B252: Insufficient Modularization | C252: net.bytebuddy.dynamic.ClassFileLocator | D252: Illegal | E252: =C252&"."&D252 -> net.bytebuddy.dynamic.ClassFileLocator.Illegal | F252: data/processed/prompts/insufficient_modularization/byte-buddy/net_bytebuddy_dynamic_ClassFileLocator_Illegal.txt | G252: 342 | H252: 0 | I252: =VLOOKUP(E252,gpt!E252:F5672,2,0) -> 0 | J252: =VLOOKUP(E252,deepseek!E252:F5672,2,0) -> 0 | K252: =VLOOKUP(E252,qwen!E252:F5672,2,0) -> 0
A253: javaparser | B253: Insufficient Modularization | C253: com.github.javaparser.ast.validator.language.level.validations.chunks | D253: NoBinaryIntegerLiteralsValidator | E253: =C253&"."&D253 -> com.github.javaparser.ast.validator.language.level.validations.chunks.NoBinaryIntegerLiteralsValidator | F253: data/processed/prompts/insufficient_modularization/javaparser/com_github_javaparser_ast_validator_language_level_validations_chunks_NoBinaryIntegerLiteralsValidator.txt | G253: 406 | H253: 0 | I253: =VLOOKUP(E253,gpt!E253:F5673,2,0) -> 0 | J253: =VLOOKUP(E253,deepseek!E253:F5673,2,0) -> 0 | K253: 0
A254: byte-buddy | B254: Insufficient Modularization | C254: net.bytebuddy.pool.TypePool | D254: ForAnnotationProperty | E254: =C254&"."&D254 -> net.bytebuddy.pool.TypePool.ForAnnotationProperty | F254: data/processed/prompts/insufficient_modularization/byte-buddy/net_bytebuddy_pool_TypePool_ForAnnotationProperty.txt | G254: 351 | H254: 0 | I254: =VLOOKUP(E254,gpt!E254:F5674,2,0) -> 0 | J254: =VLOOKUP(E254,deepseek!E254:F5674,2,0) -> 0 | K254: =VLOOKUP(E254,qwen!E254:F5674,2,0) -> 0
A255: byte-buddy | B255: Insufficient Modularization | C255: net.bytebuddy.implementation.FieldAccessor | D255: Prepared | E255: =C255&"."&D255 -> net.bytebuddy.implementation.FieldAccessor.Prepared | F255: data/processed/prompts/insufficient_modularization/byte-buddy/net_bytebuddy_implementation_FieldAccessor_Prepared.txt | G255: 352 | H255: 0 | I255: =VLOOKUP(E255,gpt!E255:F5675,2,0) -> 0 | J255: =VLOOKUP(E255,deepseek!E255:F5675,2,0) -> 0 | K255: =VLOOKUP(E255,qwen!E255:F5675,2,0) -> 0
...

Sheet gpt
A1: project | B1: file_name | C1: smell | D1: entity_type | E1: entity | F1: detection | G1: justification
A2: byte-buddy | B2: (default package)_MavenWrapperDownloader.txt | D2: class | E2: (default package).MavenWrapperDownloader | F2: 1 | G2: LOC=93 and WMC=12 indicate moderate size and complexity; NOM=6 with NOPM=1 (only one public method) implies many internal/helper methods, suggesting multiple responsibilities hidden inside the class; LCOM=0.8333 (high, near 1) shows low cohesion among methods/fields. These elements (size, internal complexity, low cohesion, few public entry points) justify that the class is insufficiently modularized and would benefit from decomposition (extraction of responsibilities into separate classes or helper objects).
A3: byte-buddy | B3: com.service.definition_ServiceDefinition.txt | D3: class | E3: com.service.definition.ServiceDefinition | F3: 0 | G3: False — the class shows no signs of Insufficient Modularization: LOC=3, NOM=1, WMC=1, NOF=0, NOPF=0, NOPM=0, fanin=0, fanout=0, LCOM=-1.0. It is very small, has a single method, no fields and minimal complexity/cohesion metrics, so there is no evidence it needs further decomposition.
A4: byte-buddy | B4: com.service.usage2_ServiceImplementation.txt | D4: class | E4: com.service.usage2.ServiceImplementation | F4: 0 | G4: The class is small and simple (loc=5, wmc=1) with a single method (nom=1, nopm=1) and no fields (nof=0, nopf=0). Cohesion metric is high/acceptable (lcom=-1.0) and there are no incoming or outgoing dependencies (fanin=0, fanout=0). Given the minimal size, low complexity, and lack of multiple responsibilities, there is no evidence that the class is insufficiently modularized.
A5: byte-buddy | B5: com.service.usage_ServiceImplementation.txt | D5: class | E5: com.service.usage.ServiceImplementation | F5: 0 | G5: Not detected: class is very small and simple — LOC=5, NOM=1, WMC=1, NOF=0, NOPF=0, NOPM=1, LCOM=-1.0, fanin=0, fanout=0. Low size, single method, low complexity and no coupling indicate no further decomposition is warranted.
A6: byte-buddy | B6: net.bytebuddy.agent.builder_AgentBuilder.Adapter.txt | D6: class | E6: net.bytebuddy.agent.builder.AgentBuilder.Adapter | F6: 0 | G6: Metrics show a very small, trivial class: LOC=21, NOM=0, NOF=0, WMC=0, fanin=0, fanout=0 and only one external dependency. There are no methods or fields to decompose and complexity is zero, so there is no evidence that further modularization is needed (LCOM=-1.0 is not indicative of missing decomposition).
A7: byte-buddy | B7: net.bytebuddy.agent.builder_AgentBuilder.Appender.txt | D7: class | E7: net.bytebuddy.agent.builder.AgentBuilder.Appender | F7: 0 | G7: The class is small and already highly cohesive/low complexity: LOC=22, NOM=0, WMC=0, NOF=1. LCOM=-1.0 indicates strong cohesion. Coupling is negligible (fanin=0, fanout=0). Given the lack of methods, low size, and low complexity, there is no evidence that the class has not been decomposed further; insufficient modularization is not detected.
A8: byte-buddy | B8: net.bytebuddy.agent.builder_AgentBuilder.Asynchronous.txt | D8: class | E8: net.bytebuddy.agent.builder.AgentBuilder.Asynchronous | F8: 1 | G8: High source size (loc: 141) combined with a non-trivial number of fields (nof: 8) while declaring zero methods (nom: 0, nopm: 0) indicates the class body contains substantial implementation that has not been decomposed into smaller methods or helper types. The mismatch between large LOC and zero reported methods suggests responsibilities or implementation details are embedded in initializers/inline code rather than modularized. WMC: 0 and LCOM: -1.0 provide no evidence of well-distributed complexity/cohesion, and the small dependency set (2 entries) implies functionality is implemented inside this class rather than delegated—together these elements justify detecting Insufficient Modularization.
A9: byte-buddy | B9: net.bytebuddy.agent.builder_AgentBuilder.AtFixedRate.txt | D9: class | E9: net.bytebuddy.agent.builder.AgentBuilder.AtFixedRate | F9: 0 | G9: The class does not exhibit signs of insufficient modularization: small size (LOC=40), very low complexity (WMC=0), no methods (nom=0), few fields (NOF=3, NOPF=0), high cohesion indicator (LCOM=-1.0), and no incoming/outgoing coupling (fanin=0, fanout=0). Only a single listed dependency (net.bytebuddy.build.HashCodeAndEqualsPlugin). Based on these metrics in isolation, the class is not large or complex enough to require further decomposition.
A10: byte-buddy | B10: net.bytebuddy.agent.builder_AgentBuilder.BatchAllocator.txt | D10: class | E10: net.bytebuddy.agent.builder.AgentBuilder.BatchAllocator | F10: 1 | G10: High size and state: LOC = 370 and number of fields (nof) = 14 while number of methods (nom) = 0. The large line count combined with many fields indicates the class is large and likely mixes responsibilities, suggesting it has not been sufficiently decomposed and would benefit from modularization.
A11: byte-buddy | B11: net.bytebuddy.agent.builder_AgentBuilder.BatchReallocator.txt | D11: class | E11: net.bytebuddy.agent.builder.AgentBuilder.BatchReallocator | F11: 0 | G11: Class is small and simple: LOC=26, NOF=1, NOM=0, WMC=0, DIT=0. Coupling is minimal (fanin=0, fanout=0) and only one external dependency (net.bytebuddy.build.HashCodeAndEqualsPlugin). These metrics indicate low size and complexity, so there is no evidence that further decomposition is needed.
A12: byte-buddy | B12: net.bytebuddy.agent.builder_AgentBuilder.BootstrapMarkerAction.txt | D12: class | E12: net.bytebuddy.agent.builder.AgentBuilder.BootstrapMarkerAction | F12: 0 | G12: The class is small and non-complex: LOC=13, NOM=0, WMC=0, NOPM=0. Coupling is minimal (fanin=0, fanout=0, single listed dependency: net.bytebuddy.dynamic.loading.ClassLoadingStrategy). With no methods or fields to decompose and very low complexity and size, there is no evidence that further decomposition is needed in isolation.
A13: byte-buddy | B13: net.bytebuddy.agent.builder_AgentBuilder.BridgeMethodImplementation.txt | D13: class | E13: net.bytebuddy.agent.builder.AgentBuilder.BridgeMethodImplementation | F13: 0 | G13: The class does not show signs of insufficient modularization: small size (loc=56), very low complexity (wmc=0), no methods to split (nom=0), only three fields (nof=3), minimal inheritance depth (dit=1), and low coupling (fanin=0, fanout=0). The cohesion metric (lcom=-1.0) does not indicate poor cohesion. Although there are a few external type references, the class's limited size and complexity mean further decomposition is not justified based on the provided metrics.
... A541: byte-buddy | B541: net.bytebuddy.benchmark.jmh_generated_StubInvocationBenchmark_jmhType_B3.txt | D541: class | E541: net.bytebuddy.benchmark.jmh.generated.StubInvocationBenchmark.jmhType.B3 | F541: 1 | G541: The class has an extremely large number of fields (nof = 256) while having no methods (nom = 0) and very low LOC (18). WMC = 0 and LCOM = -1.0 indicate absence of encapsulated behavior; DIT = 3 shows deeper inheritance but does not reduce the field bloat. The combination of many fields with no behavior/operations suggests the class has not been decomposed and should be modularized into smaller, cohesive units.
A542: byte-buddy | B542: net.bytebuddy.benchmark.jmh_generated_SuperClassInvocationBenchmark_baseline_jmhTest.txt | C542: insufficient_modularization | D542: class | E542: net.bytebuddy.benchmark.jmh.generated.SuperClassInvocationBenchmark.baseline.jmhTest | G542: {
A543: ""class"": ""net.bytebuddy.benchmark.jmh_generated.SuperClassInvocationBenchmark_baseline_jmhTest""
A544: ""detection"": true
A545: ""justification"": ""The class exhibits characteristics of Insufficient Modularization: extremely high number of fields (nof = 263) concentrated in a single class while LOC is 276 and number of methods is small (nom = 9 | B545: nopm = 8) | C545: indicating many attributes/responsibilities are not split into smaller types. Complexity is non-trivial (wmc = 42). Additionally | D545: there is no inheritance decomposition (dit = 0 | E545: nopm = 8) | F545: fanout = 0) | G545: suggesting the class itself holds much structure/behavior that could be factored out. These elements together justify that the class has not been sufficiently decomposed and would benefit from modularization/refactoring."""
A546: byte-buddy | B546: net.bytebuddy.benchmark.jmh_generated_SuperClassInvocationBenchmark_benchmarkByteBuddySpecialized_jmhTest.txt | D546: class | E546: net.bytebuddy.benchmark.jmh.generated.SuperClassInvocationBenchmark.benchmarkByteBuddySpecialized.jmhTest | F546: 1 | G546: The class exhibits signs of insufficient modularization: very high number of fields (nof = 263) combined with substantial size (loc = 276) and elevated complexity (wmc = 42) despite a relatively small number of methods (nom = 9). The disproportionate field count relative to methods and overall size suggests the class aggregates many responsibilities or data elements that could be decomposed into smaller, more focused classes or modules.
A547: byte-buddy | B547: net.bytebuddy.benchmark.jmh_generated_SuperClassInvocationBenchmark_benchmarkByteBuddyWithAccessor_jmhTest.txt | D547: class | E547: net.bytebuddy.benchmark.jmh.generated.SuperClassInvocationBenchmark.benchmarkByteBuddyWithAccessor.jmhTest | F547: 1 | G547: Detected because the class has an extremely high number of fields (nof=263) while exposing a small number of methods (nom=9, nopm=8), together with sizable size and complexity (loc=276, wmc=42). The disproportion between very large state (many fields) and relatively few operations, plus overall LOC/WMC, indicates the class aggregates too much responsibility and state and could be further decomposed to reduce size and implementation complexity.
A548: byte-buddy | B548: net.bytebuddy.benchmark.jmh_generated_SuperClassInvocationBenchmark_benchmarkByteBuddyWithPrefix_jmhTest.txt | D548: class | E548: net.bytebuddy.benchmark.jmh.generated.SuperClassInvocationBenchmark.benchmarkByteBuddyWithPrefix.jmhTest | F548: 1 | G548: The class shows signs of being a monolithic unit: very high number of fields (nof = 263) and substantial size (loc = 276) while having a relatively small set of methods (nom = 9, nopm = 8). Combined with a high complexity score (wmc = 42) this indicates many responsibilities and large internal state that could be decomposed. The lack of inheritance depth (dit = 0) implies decomposition has not been applied via subclasses. These elements together justify detecting Insufficient Modularization.
A549: byte-buddy | B549: net.bytebuddy.benchmark.jmh_generated_SuperClassInvocationBenchmark_benchmarkByteBuddyWithProxy_jmhTest.txt | D549: class | E549: net.bytebuddy.benchmark.jmh.generated.SuperClassInvocationBenchmark.benchmarkByteBuddyWithProxy.jmhTest | F549: 1 | G549: The class shows signs of insufficient modularization: extremely high number of fields (nof = 263) while having few methods (nom = 9, nopm = 8) and only moderate LOC (loc = 276). The weighted method complexity is relatively high (wmc = 42) given the small method count, indicating concentrated complexity. The disparity between a very large field set and few methods suggests multiple responsibilities or bundled state that could be split into smaller, more cohesive classes to reduce size and implementation complexity.
A550: byte-buddy | B550: net.bytebuddy.benchmark.jmh_generated_SuperClassInvocationBenchmark_benchmarkCglib_jmhTest.txt | D550: class | E550: net.bytebuddy.benchmark.jmh.generated.SuperClassInvocationBenchmark.benchmarkCglib.jmhTest | F550: 1 | G550: The class shows signs of being too large and complex to remain monolithic: very high number of features/elements (nof = 263) and large size (loc = 276) indicate heavy implementation volume; high cyclomatic/weight metric (wmc = 42) indicates substantial internal complexity. Although method count is moderate (nom = 9) and LCOM = 0.0 implies those methods are cohesive, the overall size and element count (nof = 263) together with elevated WMC justify that the class could be further decomposed to reduce size and complexity.
A551: byte-buddy | B551: net.bytebuddy.benchmark.jmh_generated_SuperClassInvocationBenchmark_benchmarkJavassist_jmhTest.txt | D551: class | E551: net.bytebuddy.benchmark.jmh.generated.SuperClassInvocationBenchmark.benchmarkJavassist.jmhTest | F551: 1 | G551: The class exhibits signs of insufficient modularization: very large number of fields (nof = 263) and substantial size (loc = 276) indicate a bloated single unit; relatively high overall complexity (wmc = 42) across its methods (nom = 9, nopm = 8) suggests concentration of behavior rather than separation; there is no internal decomposition via nested classes (nc = 0) nor inheritance (dit = 0) to distribute responsibilities, and zero fanin/fanout (fanin = 0, fanout = 0) indicates the class is self-contained and likely monolithic. These elements together justify that further decomposition would likely reduce size and implementation complexity.
A552: byte-buddy | B552: net.bytebuddy.benchmark.jmh_generated_SuperClassInvocationBenchmark_jmhType.txt | D552: class | E552: net.bytebuddy.benchmark.jmh.generated.SuperClassInvocationBenchmark.jmhType | F552: 0 | G552: Class has LOC=2, NOM=0, NOF=0, NOPM=0 and WMC=0 indicating no methods, no fields and no implementation complexity. Fanin=0 and Fanout=0 show no coupling through calls. Although DIT=4 indicates a deep inheritance level, the class itself is trivially small and contains no decomposable responsibilities, so there is no evidence of insufficient modularization.
A553: byte-buddy | B553: net.bytebuddy.benchmark.jmh_generated_SuperClassInvocationBenchmark_jmhType_B1.txt | D553: class | E553: net.bytebuddy.benchmark.jmh.generated.SuperClassInvocationBenchmark.jmhType.B1 | F553: 1 | G553: High number of fields with no behavior: nof=256 while nom=0 and wmc=0, with very low LOC=18. This large aggregation of data (256 fields) without methods or internal decomposition indicates the class groups many responsibilities/attributes and could be split into smaller classes (insufficient modularization). Additional supporting metrics: nc=1, dit=1, fanin=0, fanout=0 — the class is isolated but monolithic, reinforcing the need for further decomposition.
A554: byte-buddy | B554: net.bytebuddy.benchmark.jmh_generated_SuperClassInvocationBenchmark_jmhType_B2.txt | D554: class | E554: net.bytebuddy.benchmark.jmh.generated.SuperClassInvocationBenchmark.jmhType.B2 | F554: 0 | G554: Although the class has 12 fields (nof=12), it contains no methods (nom=0, nopm=0) and very low implementation size and complexity (loc=14, wmc=0). Coupled with zero external coupling (fanin=0, fanout=0) and a single child (nc=1, dit=2), there is no evidence of a large, complex, or multi-responsibility implementation that would benefit from further decomposition. Therefore Insufficient Modularization is not detected.
A555: byte-buddy | B555: net.bytebuddy.benchmark.jmh_generated_SuperClassInvocationBenchmark_jmhType_B3.txt | D555: class | E555: net.bytebuddy.benchmark.jmh.generated.SuperClassInvocationBenchmark.jmhType.B3 | F555: 1 | G555: The class shows signs of insufficient modularization: very high number of fields (nof=256) while having no methods (nom=0) and low lines of code (loc=18), indicating a large data aggregate concentrated in a single class. WMC=0 (no method complexity) and nom=0 imply behavior is not separated into smaller collaborating units; fanin=0 and fanout=0 show it is isolated rather than modularized. The disproportion between nof and loc/nom supports that further decomposition (splitting fields/concerns into separate classes) would reduce size and improve modularity.
A556: byte-buddy | B556: net.bytebuddy.benchmark.jmh_generated_TrivialClassCreationBenchmark_baseline_jmhTest.txt | D556: class | E556: net.bytebuddy.benchmark.jmh.generated.TrivialClassCreationBenchmark.baseline.jmhTest | F556: 1 | G556: The class shows indicators of insufficient modularization: an extremely high number of fields (nof = 263) combined with a relatively large size (loc = 275) and elevated complexity (wmc = 42). Although method count is modest (nom = 9, nopm = 8) and LCOM = 0.0 does not indicate poor cohesion, the disproportionate amount of state (263 fields) and overall complexity suggest the class encapsulates too much responsibility and would benefit from decomposition into smaller, more focused classes or components.
A557: byte-buddy | B557: net.bytebuddy.benchmark.jmh_generated_TrivialClassCreationBenchmark_benchmarkByteBuddy_jmhTest.txt | D557: class | E557: net.bytebuddy.benchmark.jmh.generated.TrivialClassCreationBenchmark.benchmarkByteBuddy.jmhTest | F557: 1 | G557: Class shows signs of insufficient modularization: large size (LOC = 275) and high method-complexity (WMC = 42); very high number of fields/elements (NOF = 263) while having relatively few methods (NOM = 9, NOPM = 8) which suggests aggregation of many responsibilities/data into a single class; fanin = 0 and fanout = 0 indicate it is self-contained rather than composed; cohesion metric LCOM = 0.0 provides no counter-evidence. Together these metrics justify decomposing the class to reduce size and complexity.
... A692: byte-buddy | B692: net.bytebuddy.build_BuildLogger.StreamWriting.txt | D692: class | E692: net.bytebuddy.build.BuildLogger.StreamWriting | F692: 0 | G692: Metrics do not indicate a decomposable, high-responsibility unit: although LOC = 114, the class has nom = 0 (no methods), nof = 1 (one field), wmc = 0 (no cyclomatic complexity), fanin = 0 and fanout = 0 (no coupling), and LCOM = -1.0 (no cohesion concerns reported). Given the lack of methods, complexity, and coupling in isolation, there is no evidence that the class requires further decomposition.
A693: byte-buddy | B693: net.bytebuddy.build_BuildLogger.txt | C693: insufficient_modularization | D693: class | E693: net.bytebuddy.build.BuildLogger | G693: {
A694: ""class"": ""net.bytebuddy.build.BuildLogger""
A695: ""detection"": true
A696: ""justification"": ""The class is a strong candidate for Insufficient Modularization: very large size (loc=478) with a non-trivial number of methods (nom=12) indicates concentrated functionality that could be split; combined with moderate overall complexity (wmc=12) and high LOC this suggests long or complex method bodies that would benefit from decomposition. The class has no inheritance (dit=0) and zero fan-in/fan-out (fanin=0 | B696: fanout=0) | C696: meaning it is an isolated | D696: self-contained unit likely carrying multiple responsibilities rather than delegating them. LCOM=-1.0 does not provide evidence of high cohesion to counter decomposition. Dependency list is minimal (net.bytebuddy.build.HashCodeAndEqualsPlugin) | E696: fanout=0)
A697: byte-buddy | B697: net.bytebuddy.build_CachedReturnPlugin.AdviceResolver.txt | D697: class | E697: net.bytebuddy.build.CachedReturnPlugin.AdviceResolver | F697: 1 | G697: The class has a large size (loc: 153) while holding multiple fields (nof: 6) and referencing many external types (12 distinct dependencies), indicating it touches multiple responsibilities and high coupling. Cohesion metrics are not clearly positive (lcom: -1.0) and there are no recorded fine-grained method counts, suggesting substantial implementation concentrated in a single class. These indicators together point to insufficient modularization — the class is large and interacts with diverse concerns and would likely benefit from decomposition.
A698: byte-buddy | B698: net.bytebuddy.build_CachedReturnPlugin.CacheFieldOffsetMapping.txt | D698: class | E698: net.bytebuddy.build.CachedReturnPlugin.CacheFieldOffsetMapping | F698: 0 | G698: The class does not exhibit Insufficient Modularization: it has very small size and complexity (loc=22), only one field (nof=1) and no methods (nom=0, wmc=0), indicating there is little to decompose. Coupling is minimal (fanin=0, fanout=0) and cohesion metric is non-problematic (lcom=-1.0). These metrics show the class is already small and simple, so further decomposition is not warranted based on the provided data.
A699: byte-buddy | B699: net.bytebuddy.build_CachedReturnPlugin.ExitAdviceByteCodeAppender.txt | D699: class | E699: net.bytebuddy.build.CachedReturnPlugin.ExitAdviceByteCodeAppender | F699: 0 | G699: The class shows no indicators of an undecomposed, overly complex implementation: LOC is modest (62), Weighted Methods per Class (wmc) = 0 and Number of Methods (nom) = 0 indicate no large method body complexity to decompose, and Number of Fields (nof) = 5 is small. Coupling is minimal (fanin = 0, fanout = 0), inheritance depth is shallow (dit = 1), and LCOM is non-indicative. Given these metrics in isolation, there is no evidence that the class should be further decomposed, so Insufficient Modularization is not detected.
A700: byte-buddy | B700: net.bytebuddy.build_CachedReturnPlugin.txt | D700: class | E700: net.bytebuddy.build.CachedReturnPlugin | F700: 1 | G700: Insufficient modularization detected: the class is large (loc=260) while exposing few methods (nom=5, nopm=5) and a moderate cyclomatic burden (wmc=11), indicating large/complex methods. It declares many fields (nof=11) but few methods, producing a high field-to-method ratio and suggesting multiple responsibilities. Cohesion is low (lcom=0.8), showing related behavior is not well concentrated. The class depends on a wide variety of unrelated subsystems (19 dependencies, e.g. net.bytebuddy.build.HashCodeAndEqualsPlugin, net.bytebuddy.dynamic.DynamicType, net.bytebuddy.implementation.Implementation, net.bytebuddy.asm.Advice), which implies it mixes responsibilities across different concerns. These factors together justify that the class has not been fully decomposed and would benefit from further modularization.
A701: byte-buddy | B701: net.bytebuddy.build_DispatcherAnnotationPlugin.txt | D701: class | E701: net.bytebuddy.build.DispatcherAnnotationPlugin | F701: 0 | G701: Class has small size and complexity: loc=44, nom=6, nopm=6 and wmc=7 indicate limited implementation surface and moderate cyclomatic complexity. Depth of inheritance is low (dit=1) and lack of children (nc=0) suggests no need to split due to subclassing. Coupling/usage metrics do not indicate broad responsibilities (fanin=0, fanout=0) and cohesion measure (lcom=-1.0) does not imply fragmented responsibilities. Given these metrics, the class does not exhibit signs of insufficient modularization that would require further decomposition.
A702: byte-buddy | B702: net.bytebuddy.build_EntryPoint.Default.txt | D702: class | E702: net.bytebuddy.build.EntryPoint.Default | F702: 0 | G702: Metrics show no evidence of an under-decomposed class: number of methods (nom) = 0 and weighted methods per class (wmc) = 0 indicate no internal behavioral complexity to split; lack of fields/methods (nof=0, nopf=0) means nothing substantial to modularize. Size is modest (loc = 72) and coupling is low (fanin = 0, fanout = 0) with only three listed type dependencies, so there is no data suggesting further decomposition would reduce size or complexity.
A703: byte-buddy | B703: net.bytebuddy.build_EntryPoint.Unvalidated.txt | D703: class | E703: net.bytebuddy.build.EntryPoint.Unvalidated | F703: 0 | G703: The class does not exhibit Insufficient Modularization: small size (LOC 35), very few fields (nof 2), no methods (nom 0) and no complexity (WMC 0), shallow inheritance (DIT 1), low coupling (fanin 0, fanout 0), and high cohesion (LCOM -1.0). These metrics indicate the class is small, simple and self-contained, so further decomposition is not warranted.
A704: byte-buddy | B704: net.bytebuddy.build_EntryPoint.txt | D704: class | E704: net.bytebuddy.build.EntryPoint | F704: 0 | G704: The class does not show signs of insufficient modularization: low method count (nom = 2) and low weighted method count (wmc = 2) indicate simple behavior; small number of fields (nof = 2); moderate size (loc = 127) but not accompanied by high complexity; very high cohesion (lcom = -1.0) and no external coupling indicated by fanin = 0 and fanout = 0. These metrics together suggest the class is adequately modular and does not require further decomposition.
A705: byte-buddy | B705: net.bytebuddy.build_HashCodeAndEqualsPlugin.AnnotationOrderComparator.txt | D705: class | E705: net.bytebuddy.build.HashCodeAndEqualsPlugin.AnnotationOrderComparator | F705: 0 | G705: Class is small and not complex: LOC=25, WMC=0, NOM=0. It has no measured coupling or interactions (fanin=0, fanout=0) and only two listed dependencies, indicating limited responsibilities. LCOM=-1.0 does not indicate a cohesion problem in the provided data. Given these metrics in isolation, there is no evidence that the class is large or multifaceted enough to require further decomposition.
A706: byte-buddy | B706: net.bytebuddy.build_HashCodeAndEqualsPlugin.InvokeSuper.txt | D706: class | E706: net.bytebuddy.build.HashCodeAndEqualsPlugin.InvokeSuper | F706: 0 | G706: Metrics do not indicate an undecomposed, complex class. LOC is 86 which is moderate, but there are 0 methods (nom=0), 0 fields (nof=0), 0 weighted method count (wmc=0) and no coupling (fanin=0, fanout=0). LCOM is -1.0 (no cohesion data). Given the absence of method/field complexity and no external coupling in the provided data, there is no evidence that further decomposition would reduce size or complexity for this class when considered in isolation.
A707: byte-buddy | B707: net.bytebuddy.build_HashCodeAndEqualsPlugin.Sort.txt | D707: class | E707: net.bytebuddy.build.HashCodeAndEqualsPlugin.Sort | F707: 0 | G707: Metrics do not indicate insufficient modularization: very small size (loc = 10), no methods (nom = 0) and no fields (nof = 0), zero complexity (wmc = 0), no children/usage (dit = 0, fanin = 0, fanout = 0). These values show the class is trivial/small and there is no evidence it should be further decomposed.
A708: byte-buddy | B708: net.bytebuddy.build_HashCodeAndEqualsPlugin.ValueMatcher.txt | D708: class | E708: net.bytebuddy.build.HashCodeAndEqualsPlugin.ValueMatcher | F708: 0 | G708: In isolation the class is small and simple: LOC=23, number of methods (nom)=0, weighted methods complexity (wmc)=0, number of fields (nof)=1, fanin=0, fanout=0. These metrics indicate no large size or implementation complexity that would benefit from further decomposition. There is no evidence of multiple responsibilities or high cohesion/complexity that justify marking it as Insufficient Modularization.
... A4027: javaparser | B4027: com.github.javaparser.resolution_MethodUsage.txt | D4027: class | E4027: com.github.javaparser.resolution.MethodUsage | F4027: 1 | G4027: The class has 24 methods (23 public), 175 LOC and a WMC of 38, indicating a relatively large public surface and moderate implementation complexity. The high number of public methods (nopm=23) suggests multiple responsibilities or API surface that could be split. The class also depends on several distinct resolution types (ResolvedReferenceTypeDeclaration, ResolvedTypeParameterDeclaration, ResolvedTypeParametersMap, ResolvedMethodDeclaration, ResolvedType), which implies it handles multiple concerns. Although LCOM=0 indicates internal cohesion, the combination of many public methods, size (LOC=175) and complexity (WMC=38) supports that further decomposition could reduce size and simplify the implementation.
A4028: javaparser | B4028: com.github.javaparser.resolution_Navigator.txt | C4028: insufficient_modularization | D4028: class | E4028: com.github.javaparser.resolution.Navigator | G4028: {
A4029: ""class"": ""com.github.javaparser.resolution.Navigator""
A4030: ""detection"": true
A4031: ""justification"": ""Class has high method count and public surface (nom=26 | B4031: nopm=22) and substantial implementation size (loc=197) with high complexity (wmc=51) | C4031: which indicate a large | D4031: multifaceted implementation. The class depends on many distinct AST node types (CompilationUnit | E4031: nopm=22) and substantial implementation size (loc=197) with high complexity (wmc=51) | F4031: SwitchStmt | G4031: FieldDeclaration | H4031: TypeDeclaration | I4031: Node | J4031: ClassOrInterfaceDeclaration | K4031: ReturnStmt | L4031: VariableDeclarator | M4031: MethodDeclaration | N4031: ConstructorDeclaration) | O4031: suggesting it handles multiple responsibilities or navigation concerns. These factors (many methods | P4031: many public methods | Q4031: high WMC/LOC | R4031: and wide variety of dependent types) justify that the class is insufficiently modular and could be decomposed into smaller | S4031: more focused components."""
A4032: javaparser | B4032: com.github.javaparser.resolution_Resolvable.txt | D4032: class | E4032: com.github.javaparser.resolution.Resolvable | F4032: 0 | G4032: Class shows no signs of insufficient modularization: LOC=3, NOM=1, WMC=1, NOF=0, NOPF=0, NOPM=0, FANIN=0, FANOUT=0, DIT=0. Very small size, single method and minimal complexity indicate no need for further decomposition.
A4033: javaparser | B4033: com.github.javaparser.resolution_Solver.txt | D4033: class | E4033: com.github.javaparser.resolution.Solver | F4033: 0 | G4033: Metrics do not indicate an undecomposed, large, or complex class: loc is only 27 (very small); nom = 13 but wmc = 13 (methods are simple, complexity per method is low); lcom = -1.0 indicates high cohesion of the methods; fanin/fanout = 0 show no coupling evidence in the given data. Together these suggest the class is small and cohesive, so there is not sufficient evidence of Insufficient Modularization (further decomposition is unlikely to reduce size or complexity).
A4034: javaparser | B4034: com.github.javaparser.resolution_SymbolDeclarator.txt | D4034: class | E4034: com.github.javaparser.resolution.SymbolDeclarator | F4034: 0 | G4034: Class is small and simple: LOC=6, NOM=1, WMC=1, no fields (NOF=0), no public fields (NOPF=0), low coupling (FANOUT=0, FANIN=0), DIT=0. These metrics indicate the class is already minimal in size and complexity and does not show signs of being insufficiently modularized.
A4035: javaparser | B4035: com.github.javaparser.resolution_SymbolResolver.txt | D4035: class | E4035: com.github.javaparser.resolution.SymbolResolver | F4035: 0 | G4035: The class is small and cohesive: LOC=18, NOM=4, WMC=4 and LCOM=-1.0 indicate low size, low implementation complexity and high cohesion. There are no fields (NOF=0) and no incoming/outgoing coupling (fanin=0, fanout=0). Given these metrics the class does not exhibit excessive size or complexity that would justify further decomposition when considered in isolation.
A4036: javaparser | B4036: com.github.javaparser.resolution_TypeSolver.txt | D4036: class | E4036: com.github.javaparser.resolution.TypeSolver | F4036: 0 | G4036: Class is small (loc=62) with a moderate number of methods (nom=10) and moderate complexity (wmc=13). Cohesion is high (lcom=-1.0) and coupling appears low (fanin=0, fanout=0, only 3 external dependencies). It has a small number of fields (nof=2) and no inheritance (dit=0). Given the compact size, good cohesion, and low coupling, there is no evidence that the class is insufficiently modularized or requires further decomposition.
A4037: javaparser | B4037: com.github.javaparser.resolution_UnsolvedSymbolException.txt | D4037: class | E4037: com.github.javaparser.resolution.UnsolvedSymbolException | F4037: 0 | G4037: Class is small and cohesive: LOC=39, NOM=6, WMC=6, NOF=3, NOPF=0. LCOM=0.0 indicates high cohesion. DIT=0 and NC=0 show no deep hierarchy pressure to decompose. Fanout=0 and no dependencies suggest no internal complexity from collaborators. These metrics do not indicate an incompletely decomposed class, so Insufficient Modularization is not detected.
A4038: javaparser | B4038: com.github.javaparser.serialization_JavaParserJsonDeserializer.txt | D4038: class | E4038: com.github.javaparser.serialization.JavaParserJsonDeserializer | F4038: 1 | G4038: The class shows signs of insufficient modularization: moderate size (loc=126) combined with high implementation complexity (wmc=22) spread over a small number of methods (nom=8) indicates concentrated complex logic. It depends on many distinct concerns/types (CompilationUnit, JavaToken, NodeList, JavaParserMetaModel, Node, PropertyMetaModel, StaticJavaParser, Position, BaseNodeMetaModel), suggesting the class handles multiple responsibilities (AST nodes, tokens, positions, meta-model handling and parsing utilities). These factors (high WMC relative to NOM, multiple unrelated dependencies, and concentrated LOC) justify that the class should be further decomposed into smaller, more focused modules.
A4039: javaparser | B4039: com.github.javaparser.serialization_JavaParserJsonSerializer.JsonNode.txt | D4039: class | E4039: com.github.javaparser.serialization.JavaParserJsonSerializer.JsonNode | F4039: 0 | G4039: The class is very small and contains no behavioral complexity: LOC=11, NOF=1, NOM=0, WMC=0. It has no incoming or outgoing coupling (fanin=0, fanout=0) and no methods to further decompose. Given its minimal size and complexity, there is no evidence it has not been sufficiently modularized.
A4040: javaparser | B4040: com.github.javaparser.serialization_JavaParserJsonSerializer.JsonRange.txt | D4040: class | E4040: com.github.javaparser.serialization.JavaParserJsonSerializer.JsonRange | F4040: 0 | G4040: Class is very small and simple: LOC=8, nof=1 (single field), nom=0 and nopf=0 (no methods), WMC=0 (no complexity). Fanin=0 and Fanout=0 indicate no coupling to decompose. Given these metrics, there is no evidence that the class is insufficiently modularized or that it should be further decomposed.
A4041: javaparser | B4041: com.github.javaparser.serialization_JavaParserJsonSerializer.JsonToken.txt | D4041: class | E4041: com.github.javaparser.serialization.JavaParserJsonSerializer.JsonToken | F4041: 0 | G4041: Class is small and not complex: LOC=8, number of fields=1, number of methods=0, WMC=0, fan-in=0, fan-out=0. With a single field, no methods, zero complexity and no dependencies, there is no evidence this class has not been decomposed further; it does not exhibit the size or implementation complexity indicative of Insufficient Modularization.
A4042: javaparser | B4042: com.github.javaparser.serialization_JavaParserJsonSerializer.JsonTokenRange.txt | D4042: class | E4042: com.github.javaparser.serialization.JavaParserJsonSerializer.JsonTokenRange | F4042: 0 | G4042: Class is very small and simple in isolation: LOC=8, number of fields=1 (nof=1), number of methods=0 (nom=0), WMC=0, DIT=0, fan-in=0, fan-out=0. There is no measurable internal complexity or many responsibilities to split (LCOM=-1.0 not indicating cohesion issues here). Given these metrics, there is no evidence that the class is insufficiently modularized.
A4043: javaparser | B4043: com.github.javaparser.serialization_JavaParserJsonSerializer.txt | D4043: class | E4043: com.github.javaparser.serialization.JavaParserJsonSerializer | F4043: 0 | G4043: Metrics do not indicate an undecomposed, oversized class: LOC=129 and NOM=6 show moderate size and small number of methods; WMC=14 is moderate complexity but not extreme; LCOM=0.0 indicates high cohesion (methods operate on related data). There is only 1 public method (NOPM=1), implying a small public surface. NOF=4 fields is modest. The listed dependencies include several internal Json* types (JsonRange, JsonNode, JsonToken, JsonTokenRange) suggesting internal decomposition is already present. Taken in isolation, these factors point away from Insufficient Modularization.
... A5422: zxing | B5422: com.google.zxing_WriterException.txt | D5422: class | E5422: com.google.zxing.WriterException | F5422: 0 | G5422: Class is small and low-complexity: LOC=14, WMC=3, NOM=3 (NOPM=3), NOF=0, NOPF=0. Coupling is nil (fanin=0, fanout=0, dependencies=[]), NC=0, LCOM=-1.0 indicates cohesion. Given the small size, low complexity, no fields and no external dependencies, there is no evidence this class is insufficiently modular or requires further decomposition.

Sheet deepseek
A1: project | B1: file_name | C1: smell | D1: entity_type | E1: entity | F1: detection | G1: justification
A2: byte-buddy | B2: (default package)_MavenWrapperDownloader.txt | D2: class | E2: (default package).MavenWrapperDownloader | F2: 1 | G2: High lack of cohesion (LCOM = 0.833) and moderate complexity (WMC = 12) with 6 methods and 6 fields indicate low internal cohesion, suggesting that further decomposition could reduce implementation complexity and size.
A3: byte-buddy | B3: com.service.definition_ServiceDefinition.txt | D3: class | E3: com.service.definition.ServiceDefinition | F3: 0 | G3: The class has only one method (nom=1), no fields (nof=0), low size (loc=3), and low complexity (wmc=1). Further decomposition would not reduce its size or implementation complexity.
A4: byte-buddy | B4: com.service.usage2_ServiceImplementation.txt | D4: class | E4: com.service.usage2.ServiceImplementation | F4: 0 | G4: The class has only one method, no fields, low lines of code (5), and low complexity (wmc=1). There is no indication that further decomposition would reduce size or complexity.
A5: byte-buddy | B5: com.service.usage_ServiceImplementation.txt | D5: class | E5: com.service.usage.ServiceImplementation | F5: 0 | G5: The class has minimal complexity with only 1 method, 5 lines of code, 0 fields, and no dependencies, indicating it is already sufficiently modularized and does not require further decomposition.
A6: byte-buddy | B6: net.bytebuddy.agent.builder_AgentBuilder.Adapter.txt | D6: class | E6: net.bytebuddy.agent.builder.AgentBuilder.Adapter | F6: 0 | G6: The class has no methods (nom=0), no fields (nof=0), and low lines of code (loc=21). Its complexity is minimal (wmc=0, lcom=-1). There is no indication that further decomposition would reduce size or complexity.
A7: byte-buddy | B7: net.bytebuddy.agent.builder_AgentBuilder.Appender.txt | D7: class | E7: net.bytebuddy.agent.builder.AgentBuilder.Appender | F7: 0 | G7: The class has only 1 field, 0 methods, and 22 lines of code, indicating minimal size and complexity. With no methods (WMC=0) and a single responsibility suggested by its name, further decomposition is unlikely to reduce size or complexity.
A8: byte-buddy | B8: net.bytebuddy.agent.builder_AgentBuilder.Asynchronous.txt | D8: class | E8: net.bytebuddy.agent.builder.AgentBuilder.Asynchronous | F8: 0 | G8: The class has 0 methods (nom=0, nopm=0) and 0 complexity (wmc=0), indicating no behavioral complexity to decompose. The 8 fields (nof=8) and 141 lines of code (loc=141) may represent a data container with extensive comments or formatting, but further decomposition is unlikely to reduce complexity or size significantly given the absence of methods.
A9: byte-buddy | B9: net.bytebuddy.agent.builder_AgentBuilder.AtFixedRate.txt | D9: class | E9: net.bytebuddy.agent.builder.AgentBuilder.AtFixedRate | F9: 0 | G9: The class has no methods (nom=0) and zero complexity (wmc=0), with only three fields (nof=3). Although loc=40 is moderate, there is no evidence of multiple responsibilities or that further decomposition would reduce size or complexity.
A10: byte-buddy | B10: net.bytebuddy.agent.builder_AgentBuilder.BatchAllocator.txt | D10: class | E10: net.bytebuddy.agent.builder.AgentBuilder.BatchAllocator | F10: 1 | G10: The class has 370 lines of code and 14 fields with no methods, indicating a large data structure that could be decomposed. The high field count (nof=14) and substantial code size (loc=370) without behavioral methods suggest insufficient decomposition of responsibilities.
A11: byte-buddy | B11: net.bytebuddy.agent.builder_AgentBuilder.BatchReallocator.txt | D11: class | E11: net.bytebuddy.agent.builder.AgentBuilder.BatchReallocator | F11: 0 | G11: Class has minimal complexity with 0 methods (nom=0, nopm=0), only 1 field (nof=1), and low size (loc=26). No methods exist to decompose, and the single field suggests the class already represents a minimal cohesive unit.
A12: byte-buddy | B12: net.bytebuddy.agent.builder_AgentBuilder.BootstrapMarkerAction.txt | D12: class | E12: net.bytebuddy.agent.builder.AgentBuilder.BootstrapMarkerAction | F12: 0 | G12: The class has no methods (nom=0) and no fields (nof=0), with low lines of code (loc=13) and zero weighted methods per class (wmc=0). This indicates minimal size and complexity, so further decomposition is not warranted.
A13: byte-buddy | B13: net.bytebuddy.agent.builder_AgentBuilder.BridgeMethodImplementation.txt | D13: class | E13: net.bytebuddy.agent.builder.AgentBuilder.BridgeMethodImplementation | F13: 1 | G13: The class has 56 lines of code (loc) but 0 methods (nom). A class with significant size (loc) and no methods suggests that its functionality is not decomposed into discrete, reusable units. This indicates insufficient modularization, as the class likely contains inline or monolithic code that could be broken down into methods to reduce size and complexity.
... A5413: zxing | B5413: com.google.zxing_WriterException.txt | D5413: class | E5413: com.google.zxing.WriterException | F5413: 0 | G5413: Class has minimal complexity with only 3 methods, 14 lines of code, and 0 fields. All methods are public, indicating a simple exception class. No dependencies suggest it is already a focused, single-responsibility unit.

Sheet qwen
A1: project | B1: file_name | C1: smell | D1: entity_type | E1: entity | F1: detection | G1: justification
A2: byte-buddy | B2: (default package).MavenWrapperDownloader | D2: class | E2: (default package).MavenWrapperDownloader | F2: 0 | G2: The class has reasonable size (93 loc) and complexity (WMC=12) for its functionality. With 6 methods and 6 fields, the class maintains a cohesive structure. The LCOM value of 0.833 suggests good cohesion within the class. The absence of dependencies and fan-in/fan-out indicates it's a self-contained utility class, which is appropriately modularized for its purpose as a Maven wrapper downloader.
A3: byte-buddy | B3: com.service.definition.ServiceDefinition | D3: class | E3: com.service.definition.ServiceDefinition | F3: 0 | G3: The class has only 1 method (nom=1, wmc=1), 0 fields (nof=0), and very low complexity (loc=3). The minimal size and complexity indicate sufficient modularization has been achieved.
A4: byte-buddy | B4: com.service.usage2.ServiceImplementation | D4: class | E4: com.service.usage2.ServiceImplementation | F4: 0 | G4: The class has only 1 method (nom=1, nopm=1), 5 lines of code (loc=5), and minimal complexity (wmc=1). With such a small size and low complexity, the class does not exhibit insufficient modularization as it is already sufficiently decomposed.
A5: byte-buddy | B5: com.service.usage.ServiceImplementation | D5: class | E5: com.service.usage.ServiceImplementation | F5: 0 | G5: The class has only 1 method (nom=1, nopm=1), 5 lines of code (loc=5), and no fields (nof=0, nopf=0). The low complexity metrics (wmc=1) and minimal size indicate this class is already sufficiently modularized and does not require further decomposition.
A6: byte-buddy | B6: net.bytebuddy.agent.builder.AgentBuilder.Adapter | D6: class | E6: net.bytebuddy.agent.builder.AgentBuilder.Adapter | F6: 0 | G6: The class has very low complexity with only 21 lines of code, 0 methods, 0 fields, and 0 weighted method count. The class appears to be a simple adapter implementation that does not exhibit signs of insufficient modularization. There is no evidence of excessive size or implementation complexity that would warrant further decomposition.
A7: byte-buddy | B7: net.bytebuddy.agent.builder.AgentBuilder.Appender | D7: class | E7: net.bytebuddy.agent.builder.AgentBuilder.Appender | F7: 0 | G7: The class has very low complexity with only 1 field (nof=1), 0 methods (nom=0), 22 lines of code (loc=22), and weighted method count of 0 (wmc=0). The low number of fields and methods indicates minimal implementation complexity that does not warrant further decomposition. The class appears to be a simple data holder or minimal implementation that does not exhibit the characteristics of insufficient modularization.
A8: byte-buddy | B8: net.bytebuddy.agent.builder.AgentBuilder.Asynchronous | D8: class | E8: net.bytebuddy.agent.builder.AgentBuilder.Asynchronous | F8: 0 | G8: The class has only 8 fields (nof=8) and 0 methods (nom=0), with a relatively small size of 141 lines of code (loc=141). The lack of methods (wmc=0, nopm=0) and minimal complexity indicators suggest this is likely a simple data holder or configuration class rather than a complex class suffering from insufficient modularization. The class does not exhibit high complexity or size that would indicate a need for further decomposition.
A9: byte-buddy | B9: net.bytebuddy.agent.builder.AgentBuilder.AtFixedRate | D9: class | E9: net.bytebuddy.agent.builder.AgentBuilder.AtFixedRate | F9: 0 | G9: The class has very low complexity with only 3 fields (nof=3), 0 methods (nom=0), 40 lines of code (loc=40), and 0 weighted method count (wmc=0). The low number of fields and absence of methods indicate minimal implementation complexity that does not warrant further decomposition. The class appears to be a simple data holder or configuration class rather than a complex class requiring modularization.
A10: byte-buddy | B10: net.bytebuddy.agent.builder.AgentBuilder.BatchAllocator | D10: class | E10: net.bytebuddy.agent.builder.AgentBuilder.BatchAllocator | F10: 1 | G10: The class has 14 fields (nof=14) and 370 lines of code (loc=370), indicating high size and complexity. The lack of methods (nom=0) suggests potential issues with decomposition. With 3 dependencies and significant size, the class likely contains multiple responsibilities that could be separated into smaller, more focused modules.
A11: byte-buddy | B11: net.bytebuddy.agent.builder.AgentBuilder.BatchReallocator | D11: class | E11: net.bytebuddy.agent.builder.AgentBuilder.BatchReallocator | F11: 0 | G11: The class has very low complexity with only 1 field (nof=1), 0 methods (nom=0, wmc=0), 26 lines of code (loc=26), and no dependencies (fanin=0, fanout=0). The class appears to be a simple data holder or configuration class with minimal functionality that does not warrant further decomposition. No signs of insufficient modularization are present given the minimal scope and complexity of this class.
A12: byte-buddy | B12: net.bytebuddy.agent.builder.AgentBuilder.BootstrapMarkerAction | D12: class | E12: net.bytebuddy.agent.builder.AgentBuilder.BootstrapMarkerAction | F12: 0 | G12: The class has very low complexity with only 13 lines of code, 0 methods, 0 fields, and WMC of 0. The lack of methods and fields indicates minimal functionality that does not warrant further decomposition. The class appears to be a simple marker or configuration class rather than a complex entity requiring modularization.
A13: byte-buddy | B13: net.bytebuddy.agent.builder.AgentBuilder.BridgeMethodImplementation | D13: class | E13: net.bytebuddy.agent.builder.AgentBuilder.BridgeMethodImplementation | F13: 0 | G13: The class has low complexity with only 3 fields (nof=3), 0 methods (nom=0), 56 lines of code (loc=56), and weighted method count of 0 (wmc=0). The lack of methods and low field count indicate minimal implementation complexity that does not warrant further decomposition.
... A475: byte-buddy | B475: net.bytebuddy.asm.MemberSubstitution.Source | D475: class | E475: net.bytebuddy.asm.MemberSubstitution.Source | F475: 0 | G475: The class has only 2 fields (nof=2), no methods (nom=0, wmc=0), and relatively low lines of code (loc=162). The lack of methods and low field count indicate it is already well-decomposed and does not exhibit insufficient modularization.
A476: byte-buddy | B476: net.bytebuddy.asm.MemberSubstitution.Step | C476: insufficient_modularization | D476: class | E476: MemberSubstitution.Step | G476: ```json_x000D_ {_x000D_ "class": "net.bytebuddy.asm.MemberSubstitution.Step",_x000D_ "detection": true,_x000D_ "justification": "The class has 191 fields (nof=191) and 4013 lines of code (loc=4013), indicating excessive size and complexity for a single class. The
A477: byte-buddy | B477: net.bytebuddy.asm.MemberSubstitution.Stubbing | D477: class | E477: net.bytebuddy.asm.MemberSubstitution.Stubbing | F477: 0 | G477: The class has very low complexity with only 23 lines of code (loc), zero methods (nom), zero fields (nof), and zero weighted method count (wmc). The low size and complexity metrics indicate that further decomposition would not provide significant benefits for reducing size or implementation complexity.
A478: byte-buddy | B478: net.bytebuddy.asm.MemberSubstitution.SubstitutingMethodVisitor | D478: class | E478: net.bytebuddy.asm.MemberSubstitution.SubstitutingMethodVisitor | F478: 0 | G478: The class has 12 fields (nof=12) and 234 lines of code (loc=234), which indicates a moderate size. With 0 methods (nom=0) and 0 public methods (nopm=0), the class appears to be a specialized visitor implementation. The low number of methods relative to fields suggests it may be a data-focused class rather than a behaviorally complex one. While the LOC count is somewhat high, the metrics do not clearly indicate insufficient modularization as the class seems to serve a specific focused purpose within the ASM framework.
A479: byte-buddy | B479: net.bytebuddy.asm.MemberSubstitution.Substitution | D479: class | E479: net.bytebuddy.asm.MemberSubstitution.Substitution | F479: 1 | G479: The class has 215 fields and 4607 lines of code, indicating excessive size and complexity for a single class. The high number of dependencies (23 external types) suggests it has too many responsibilities and could benefit from decomposition into smaller, more focused classes. The lack of methods (0) despite having many fields indicates poor encapsulation and design, supporting the presence of Insufficient Modularization.
A480: byte-buddy | B480: net.bytebuddy.asm.MemberSubstitution.Target | D480: class | E480: net.bytebuddy.asm.MemberSubstitution.Target | F480: 0 | G480: The class has only 5 fields (nof=5) and 0 methods (nom=0), with 117 lines of code (loc=117). While the LOC is relatively high for the number of methods, this appears to be a data class or value object that holds member substitution target information. The lack of methods (wmc=0) and simple structure without complex behavior does not indicate insufficient modularization - it's appropriately simple for its purpose.
A481: byte-buddy | B481: net.bytebuddy.asm.MemberSubstitution.TypePoolResolver | D481: class | E481: net.bytebuddy.asm.MemberSubstitution.TypePoolResolver | F481: 0 | G481: The class has only 3 fields (nof=3) and 0 methods (nom=0), with a relatively small size of 91 lines of code (loc=91). The lack of methods (wmc=0) and simple field structure suggests it is already well-decomposed and does not exhibit complexity that would warrant further modularization. The class appears to be a simple data holder or configuration class rather than a complex entity requiring decomposition.
A482: byte-buddy | B482: net.bytebuddy.asm.MemberSubstitution.Unbound | D482: class | E482: net.bytebuddy.asm.MemberSubstitution.Unbound | F482: 0 | G482: The class has very low complexity with only 2 fields, 0 methods, and 28 lines of code. The Weighted Methods per Class (wmc) is 0, indicating minimal implementation complexity. With such low size and complexity metrics, further decomposition would not provide meaningful benefits for reducing size or implementation complexity.
A483: byte-buddy | B483: net.bytebuddy.asm.MemberSubstitution.Unresolved | D483: class | E483: net.bytebuddy.asm.MemberSubstitution.Unresolved | F483: 0 | G483: The class has very low complexity with 0 methods (nom=0, nopm=0), 0 fields (nof=0, nopf=0), and only 19 lines of code (loc=19). The weighted method count is 0 (wmc=0) and there are no dependencies on other classes (fanout=0). This indicates a minimal, focused class that does not exhibit signs of insufficient modularization as it is already highly decomposed.
A484: byte-buddy | B484: net.bytebuddy.asm.MemberSubstitution.Value | D484: class | E484: net.bytebuddy.asm.MemberSubstitution.Value | F484: 0 | G484: The class has very low complexity with 0 methods (nom=0, nopm=0), 0 lines of code (loc=36 but this appears to be the file loc not class loc), and 0 weighted method count (wmc=0). The lack of methods and low complexity indicates insufficient data to determine insufficient modularization, and the class appears to be a simple value object or data holder that does not require further decomposition.
A485: byte-buddy | B485: net.bytebuddy.asm.MemberSubstitution.WithCustomMapping | D485: class | E485: net.bytebuddy.asm.MemberSubstitution.WithCustomMapping | F485: 1 | G485: The class has a high Lines of Code (LOC) value of 402, which indicates it is quite large and potentially complex. With only 2 fields (nof=2) and no methods (nom=0), the class appears to have insufficient internal structure and decomposition. The high LOC combined with minimal internal elements suggests the class could benefit from further modularization to reduce its size and implementation complexity.
A486: byte-buddy | B486: net.bytebuddy.asm.MemberSubstitution.WithExplicitType | D486: class | E486: net.bytebuddy.asm.MemberSubstitution.WithExplicitType | F486: 0 | G486: The class has very low complexity with only 1 field (nof=1), 0 methods (nom=0), 25 lines of code (loc=25), and minimal coupling metrics (wmc=0, nc=0, fanin=0, fanout=0). The low number of fields and methods indicates it is already well decomposed and does not exhibit insufficient modularization.
A487: byte-buddy | B487: net.bytebuddy.asm.MemberSubstitution.WithImplicitType | D487: class | E487: net.bytebuddy.asm.MemberSubstitution.WithImplicitType | F487: 0 | G487: The class has very low complexity with only 16 lines of code (loc), zero methods (nom), zero fields (nof), and zero weighted method count (wmc). The lack of methods and fields indicates minimal implementation complexity that does not warrant further decomposition. While the class has dependencies on 4 external classes, this represents typical usage patterns rather than insufficient modularization since the class itself remains simple and focused.
A488: byte-buddy | B488: net.bytebuddy.asm.MemberSubstitution.WithParameterSupportOnly | D488: class | E488: net.bytebuddy.asm.MemberSubstitution.WithParameterSupportOnly | F488: 0 | G488: The class has very low complexity with 0 methods (nom=0, nopm=0), 0 fields (nof=0, nopf=0), and only 12 lines of code (loc=12). The WMC is 0 indicating no method complexity. While it has dependencies on MethodDescription and AnnotationDescription, the class itself is minimal and does not exhibit signs of insufficient modularization as it is already highly decomposed.
... A3169: gson | B3169: com.google.gson.internal.bind.EnumTypeAdapter | D3169: class | E3169: com.google.gson.internal.bind.EnumTypeAdapter | F3169: 0 | G3169: The class has a low number of fields (4), methods (4), and relatively small size (65 LOC). The weighted method count (12) indicates moderate complexity but is not excessive for this class size. The lack of inheritance (DIT=1) and low coupling (no fan-in/fan-out) suggest appropriate modularization. The class appears to be a focused adapter implementation with reasonable responsibilities.
A3170: gson | B3170: com.google.gson.internal.bind.JavaTimeTypeAdapters | C3170: insufficient_modularization | D3170: class | E3170: JavaTimeTypeAdapters | G3170: ```json_x000D_ {_x000D_ "class": com.google.gson.internal.bind.JavaTimeTypeAdapters,_x000D_ "detection": true,_x000D_ "justification": "The class has high complexity with 33 methods (nom), 82 weighted method count (wmc), and 317 lines of code (loc). The lack of modularization is evident through the high number of methods and complexity metrics, suggesting the class could benefit from decomposition into smaller, more focused components. The LCOM value of 0.8787878787878788 indicates poor cohesion, supporting the need for better modularization."_x000D_ }_x000D_ ```
A3171: gson | B3171: com.google.gson.internal.bind.JsonAdapterAnnotationTypeAdapterFactory.DummyTypeAdapterFactory | D3171: class | E3171: com.google.gson.internal.bind.JsonAdapterAnnotationTypeAdapterFactory.DummyTypeAdapterFactory | F3171: 0 | G3171: The class has very low complexity with 0 methods (nom=0, nopm=0), 0 fields (nof=0, nopf=0), and only 5 lines of code (loc=5). The Weighted Method Count is 0 (wmc=0) and there are no dependencies (fanin=0, fanout=0). This indicates a minimal, well-decomposed class that does not exhibit insufficient modularization.
A3172: gson | B3172: com.google.gson.internal.bind.JsonAdapterAnnotationTypeAdapterFactory | D3172: class | E3172: com.google.gson.internal.bind.JsonAdapterAnnotationTypeAdapterFactory | F3172: 0 | G3172: The class has moderate complexity with 7 methods and WMC of 18, but LCOM of 0.0 indicates good cohesion. With only 109 lines of code and 4 fields, the class size is reasonable. The class appears to have a single, well-defined responsibility as a type adapter factory, and there's no clear indication that further decomposition would significantly reduce complexity or improve maintainability.
A3173: gson | B3173: com.google.gson.internal.bind.JsonElementTypeAdapter | D3173: class | E3173: com.google.gson.internal.bind.JsonElementTypeAdapter | F3173: 1 | G3173: The class has high Weighted Methods per Class (WMC=29) and a large number of Lines of Code (LOC=117), indicating high complexity that could be reduced through further decomposition. The class also has a moderate Lack of Cohesion in Methods (LCOM=0.6), suggesting that the methods may not be tightly related and could benefit from being split into more cohesive modules. With 5 methods and high WMC, the class likely contains methods with complex implementations that could be broken down into smaller, more manageable components.
A3174: gson | B3174: com.google.gson.internal.bind.JsonTreeReader | D3174: class | E3174: com.google.gson.internal.bind.JsonTreeReader | F3174: 1 | G3174: The class has 30 methods (nom=30) with 22 public methods (nopm=22), high weighted method count (wmc=70), and 285 lines of code (loc=285). These metrics indicate high complexity and size that could benefit from further decomposition into smaller, more manageable modules. The class implements multiple responsibilities for handling JSON tree reading operations, suggesting insufficient modularization.
A3175: gson | B3175: com.google.gson.internal.bind.JsonTreeWriter | D3175: class | E3175: com.google.gson.internal.bind.JsonTreeWriter | F3175: 1 | G3175: The class has 23 methods (nom) with 42 weighted method count (wmc), indicating high complexity. The large number of methods (23) and high WMC (42) suggest the class could benefit from decomposition to reduce size and implementation complexity. With 179 lines of code (loc) and 5 fields (nof), the class contains substantial functionality that could be better modularized.
A3176: gson | B3176: com.google.gson.internal.bind.MapTypeAdapterFactory.Adapter | D3176: class | E3176: com.google.gson.internal.bind.MapTypeAdapterFactory.Adapter | F3176: 0 | G3176: The class has only 3 fields (nof=3) and 0 methods (nom=0), with a relatively small size of 112 lines of code (loc=112). The lack of methods (wmc=0) and simple structure indicates it is already well-decomposed and does not exhibit insufficient modularization.
A3177: gson | B3177: com.google.gson.internal.bind.MapTypeAdapterFactory | D3177: class | E3177: com.google.gson.internal.bind.MapTypeAdapterFactory | F3177: 0 | G3177: The class has low complexity metrics (WMC=4, NOM=3, LOF=147), single inheritance level (DIT=1), and no internal coupling issues (LCOM=0.0). The number of fields (NOF=5) and methods (NOM=3) are reasonable for a factory class. While it has several dependencies (11 external classes), this is typical for a type adapter factory in Gson framework. The class does not exhibit signs of being overly large or complex that would warrant further decomposition.
A3178: gson | B3178: com.google.gson.internal.bind.NumberTypeAdapter | D3178: class | E3178: com.google.gson.internal.bind.NumberTypeAdapter | F3178: 0 | G3178: The class has moderate complexity with 6 methods (nom=6) and weighted method count of 10 (wmc=10), which is manageable. The lines of code (loc=42) is relatively small. The lack of fields (nof=2, nc=0) and low coupling (fanin=0, fanout=0) suggests good separation of concerns. The LCOM value of 0.5 indicates reasonable cohesion. The class appears to be well-focused on its responsibility as a type adapter for numbers without clear indications of needing further decomposition.
A3179: gson | B3179: com.google.gson.internal.bind.ObjectTypeAdapter | D3179: class | E3179: com.google.gson.internal.bind.ObjectTypeAdapter | F3179: 1 | G3179: The class has high complexity with WMC of 28 and 8 methods, indicating it handles too many responsibilities. The LOC of 119 suggests the class is doing too much work for a single unit of functionality. The class has 3 fields and 8 methods with only 4 private methods, suggesting poor encapsulation and potential for decomposition. The high number of dependencies (9) indicates the class is tightly coupled to many external components, which could be reduced through better modularization.
A3180: gson | B3180: com.google.gson.internal.bind.ReflectiveTypeAdapterFactory.Adapter | D3180: class | E3180: com.google.gson.internal.bind.ReflectiveTypeAdapterFactory.Adapter | F3180: 0 | G3180: The class has low complexity with only 68 lines of code, 1 field, and 0 methods. The WMC is 0 indicating minimal method complexity. While the class could potentially be decomposed further, its current size and complexity are not sufficient to warrant the Insufficient Modularization smell. The class appears to be a simple adapter implementation with minimal functionality that does not require further decomposition.
A3181: gson | B3181: com.google.gson.internal.bind.ReflectiveTypeAdapterFactory.BoundField | D3181: class | E3181: com.google.gson.internal.bind.ReflectiveTypeAdapterFactory.BoundField | F3181: 0 | G3181: The class has very low complexity with only 3 fields, 0 methods, and 28 lines of code. The WMC is 0 indicating no method complexity, and there are no dependencies. The class appears to be a simple data holder or minimal implementation that does not exhibit signs of insufficient modularization.
A3182: gson | B3182: com.google.gson.internal.bind.ReflectiveTypeAdapterFactory.FieldReflectionAdapter | D3182: class | E3182: com.google.gson.internal.bind.ReflectiveTypeAdapterFactory.FieldReflectionAdapter | F3182: 0 | G3182: The class has very low complexity with only 1 field, 0 methods, 16 lines of code, and 0 weighted method complexity. While it only has one dependency, the metrics indicate a highly cohesive and simple class that does not exhibit signs of insufficient modularization. The class appears to be appropriately decomposed for its current functionality.
... A3597: javaparser | B3597: com.github.javaparser.ast.validator.language.level.validations.Java15Validator | D3597: class | E3597: com.github.javaparser.ast.validator.language_level_validations.Java15Validator | F3597: 0 | G3597: The class has low complexity (WMC=1, LOC=10), single method (NOM=1), and minimal responsibilities (NOF=0, NOPF=0). The depth of inheritance tree is high (DIT=18) but this indicates it's part of a well-structured inheritance hierarchy rather than insufficient modularization. The class appears to be properly focused with no evidence of needing further decomposition.
A3598: javaparser | B3598: com.github.javaparser.ast.validator.language.level.validations.Java16PreviewValidator | C3598: insufficient_modularization | D3598: class | E3598: Java16PreviewValidator | G3598: ```json_x000D_ {_x000D_ "class": com.github.javaparser.ast.validator.language_level_validations.Java16PreviewValidator,_x000D_ "detection": false,_x000D_ "justification": "The class has very low complexity (WMC=1, LOC=9, NOM=1) and no fields (NOF=0), indicating it is already well decomposed. The depth of inheritance (DIT=20) suggests it inherits from a deep hierarchy, but this does not indicate insufficient modularization at this level. The class appears to be a simple, focused validator with minimal responsibilities."_x000D_ }_x000D_ ```
A3599: javaparser | B3599: com.github.javaparser.ast.validator.language.level.validations.Java16Validator | D3599: class | E3599: com.github.javaparser.ast.validator.language_level_validations.Java16Validator | F3599: 0 | G3599: The class has low complexity (WMC=1, LOC=16), single method (NOM=1), no fields (NOF=0), and reasonable encapsulation (NC=2). While DIT=19 indicates deep inheritance, this reflects appropriate specialization in a validation hierarchy rather than insufficient modularization. The class appears properly focused with minimal responsibilities.
A3600: javaparser | B3600: com.github.javaparser.ast.validator.language.level.validations.Java17PreviewValidator | D3600: class | E3600: com.github.javaparser.ast.validator.language_level_validations.Java17PreviewValidator | F3600: 0 | G3600: The class has only 1 method (nom=1, nopm=1) and 9 lines of code (loc=9), indicating minimal size and complexity. The weighted method count (wmc=1) shows low implementation complexity. The depth of inheritance tree (dit=21) indicates it's part of a well-established hierarchy but doesn't contribute to insufficient modularization at this level. With such minimal functionality and low complexity, further decomposition would not provide benefits.
A3601: javaparser | B3601: com.github.javaparser.ast.validator.language.level.validations.Java17Validator | D3601: class | E3601: com.github.javaparser.ast.validator.language_level_validations.Java17Validator | F3601: 0 | G3601: The class has low complexity with only 1 method (nom=1, wmc=1), minimal lines of code (loc=15), and simple structure (nof=2, nc=2). The low LCOM value (0.0) indicates good cohesion, and the low DIT (20) suggests it's not deeply nested in inheritance hierarchy. The class appears to be sufficiently modularized with focused responsibilities.
A3602: javaparser | B3602: com.github.javaparser.ast.validator.language.level.validations.Java18Validator | D3602: class | E3602: com.github.javaparser.ast.validator.language_level_validations.Java18Validator | F3602: 0 | G3602: The class has only 1 method (nom=1, nopm=1), very low complexity (wmc=1), small size (loc=9), and no fields (nof=0, nopf=0). The low number of methods and minimal complexity indicate that further decomposition would not provide meaningful benefits for reducing size or implementation complexity.
A3603: javaparser | B3603: com.github.javaparser.ast.validator.language.level.validations.Java19Validator | D3603: class | E3603: com.github.javaparser.ast.validator.language_level_validations.Java19Validator | F3603: 0 | G3603: The class has only 1 method (nom=1, nopm=1), very low complexity (wmc=1), small size (loc=9), and no fields (nof=0, nopf=0). The low number of methods and minimal complexity indicate that further decomposition is not necessary, as the class is already sufficiently modularized.
A3604: javaparser | B3604: com.github.javaparser.ast.validator.language.level.validations.Java1.0Validator | D3604: class | E3604: com.github.javaparser.ast.validator.language_level_validations.Java1_0Validator | F3604: 1 | G3604: The class has 30 fields (nof=30) and 125 lines of code (loc=125) but only 1 method (nom=1), indicating high complexity and insufficient decomposition. The high number of fields relative to methods suggests the class is doing too much and could benefit from further modularization to reduce size and implementation complexity.
A3605: javaparser | B3605: com.github.javaparser.ast.validator.language.level.validations.Java1.1Validator | D3605: class | E3605: com.github.javaparser.ast.validator.language_level_validations.Java1_1Validator | F3605: 0 | G3605: The class has low complexity (WMC=1, LOC=14), single responsibility (NOM=1, NOF=1), and no external dependencies being used (fanin=0, fanout=0). The class appears to be well-decomposed and does not exhibit signs of insufficient modularization.
A3606: javaparser | B3606: com.github.javaparser.ast.validator.language.level.validations.Java1.2Validator | D3606: class | E3606: com.github.javaparser.ast.validator.language_level_validations.Java1_2Validator | F3606: 0 | G3606: The class has low complexity with only 1 method (nom=1, wmc=1), minimal lines of code (loc=12), single nested class (nc=1), and no field declarations (nof=2 includes inherited fields). The low method count, low cyclomatic complexity, and small size indicate sufficient modularization without need for further decomposition.
A3607: javaparser | B3607: com.github.javaparser.ast.validator.language.level.validations.Java1.3Validator | D3607: class | E3607: com.github.javaparser.ast.validator.language_level_validations.Java1_3Validator | F3607: 0 | G3607: The class has only 1 method (nom=1, nopm=1), very low complexity (wmc=1), and minimal lines of code (loc=8). The low number of methods and complexity metrics indicate that the class is already well-decomposed and does not exhibit insufficient modularization.
A3608: javaparser | B3608: com.github.javaparser.ast.validator.language.level.validations.Java1.4Validator | D3608: class | E3608: com.github.javaparser.ast.validator.language_level_validations.Java1_4Validator | F3608: 0 | G3608: The class has low complexity (WMC=1, LOC=10), single method (NOM=1), and no fields (NOF=0). While DIT=7 indicates deep inheritance, this is likely appropriate for a validator hierarchy. The class appears to be properly modularized with focused responsibility.
A3609: javaparser | B3609: com.github.javaparser.ast.validator.language.level.validations.Java20Validator | D3609: class | E3609: com.github.javaparser.ast.validator.language_level_validations.Java20Validator | F3609: 0 | G3609: The class has very low complexity (WMC=1, LOC=9, NOM=1) and no fields (NOF=0, NOPF=0), indicating it is already well decomposed. The class implements a single method with minimal functionality, which is appropriate for its purpose as a validator. There is no evidence of insufficient modularization as the class is simple and focused.
A3610: javaparser | B3610: com.github.javaparser.ast.validator.language.level.validations.Java21Validator | D3610: class | E3610: com.github.javaparser.ast.validator.language_level_validations.Java21Validator | F3610: 0 | G3610: The class has very low complexity with only 1 method (nom=1, nopm=1), low lines of code (loc=12), and minimal complexity metrics (wmc=1, nc=1). The class appears to be sufficiently modularized given its simple nature and low complexity.
... A3612: javaparser | B3612: com.github.javaparser.ast.validator.language.level.validations.Java23Validator | D3612: class | E3612: com.github.javaparser.ast.validator.language_level_validations.Java23Validator | F3612: 0 | G3612: The class has only 1 method (nom=1, nopm=1), 0 fields (nof=0, nopf=0), and 8 lines of code (loc=8) with minimal complexity (wmc=1). The low number of methods and fields, combined with the small size and simple structure, indicates this class is already sufficiently modularized and does not require further decomposition.
A3613: javaparser | B3613: com.github.javaparser.ast.validator.language.level.validations.Java24Validator | C3613: insufficient_modularization | D3613: class | E3613: Java24Validator | G3613: ```json_x000D_ {_x000D_ "class": com.github.javaparser.ast.validator.language_level_validations.Java24Validator",_x000D_ "detection": false,_x000D_ "justification": "The class has very low complexity with only 1 method (nom=1, nopm=1), low lines of code (loc=8), and minimal complexity metrics (wmc=1). The class appears to be sufficiently modularized given its simple nature and single responsibility."_x000D_ }_x000D_ ```
A3614: javaparser | B3614: com.github.javaparser.ast.validator.language.level.validations.Java25Validator | D3614: class | E3614: com.github.javaparser.ast.validator.language_level_validations.Java25Validator | F3614: 0 | G3614: The class has only 1 method (nom=1, nopm=1) and 10 lines of code (loc=10), which indicates minimal complexity and size. The Weighted Method Count (wmc=1) is also very low, suggesting simple implementation complexity. There are no fields (nof=0, nopf=0) and no dependencies (fanin=0, fanout=0), indicating a simple, focused class that does not require further decomposition.
A3615: javaparser | B3615: com.github.javaparser.ast.validator.language.level.validations.Java5Validator | D3615: class | E3615: com.github.javaparser.ast.validator.language_level_validations.Java5Validator | F3615: 0 | G3615: The class has low complexity with only 1 method (nom=1, wmc=1), small size (loc=46), single nested class (nc=1), and no external dependencies (fanin=0, fanout=0). The low LCOM value (0.0) indicates good cohesion. While it inherits from a deep hierarchy (dit=8), the class itself is sufficiently simple and well-contained, showing no signs of insufficient modularization.
A3616: javaparser | B3616: com.github.javaparser.ast.validator.language.level.validations.Java6Validator | D3616: class | E3616: com.github.javaparser.ast.validator.language_level_validations.Java6Validator | F3616: 0 | G3616: The class has very low complexity with only 1 method (nom=1, nopm=1), low lines of code (loc=8), low weighted method count (wmc=1), and only 1 class component (nc=1). These metrics indicate the class is already well-decomposed and does not exhibit insufficient modularization.
A3617: javaparser | B3617: com.github.javaparser.ast.validator.language.level.validations.Java7Validator | D3617: class | E3617: com.github.javaparser.ast.validator.language_level_validations.Java7Validator | F3617: 0 | G3617: The class has low complexity with only 1 method (nom=1, wmc=1), minimal lines of code (loc=30), single nested class (nc=1), and no field declarations (nof=2 refers to inherited fields). The low method count and complexity metrics indicate sufficient modularization has been achieved.
A3618: javaparser | B3618: com.github.javaparser.ast.validator.language.level.validations.Java8Validator | D3618: class | E3618: com.github.javaparser.ast.validator.language_level_validations.Java8Validator | F3618: 0 | G3618: The class has low complexity (WMC=1, LOC=25), single responsibility (LCOM=0.0 indicating high cohesion), minimal method count (NOM=1), and simple inheritance structure (DIT=11 but only 1 method). The class appears to be sufficiently modularized with focused functionality.
A3619: javaparser | B3619: com.github.javaparser.ast.validator.language.level.validations.Java9Validator | D3619: class | E3619: com.github.javaparser.ast.validator.language_level_validations.Java9Validator | F3619: 0 | G3619: The class has low complexity (WMC=1, LOC=21, NOM=1) and shows no signs of insufficient modularization. It has a single method (NOM=1, NOPM=1) with low cyclomatic complexity (WMC=1), indicating it is already well-decomposed. The class has minimal responsibilities with only 3 fields and no public fields. The depth of inheritance (DIT=12) suggests it's part of a well-structured hierarchy, and the low LCOM value (0.0) indicates good cohesion. Fan-in and fan-out values of 0 suggest it's not heavily coupled, which is consistent with a well-modularized design.
A3620: javaparser | B3620: com.github.javaparser.ast.validator.language.level.validations.UpgradeJavaMessage | D3620: class | E3620: com.github.javaparser.ast.validator.language_level_validations.UpgradeJavaMessage | F3620: 0 | G3620: The class has only 3 methods (nom=3) and 3 fields (nof=3) with low complexity (wmc=3, loc=34). The lack of dependencies (fanin=0, fanout=0) and simple structure indicates it is already well modularized. No evidence of insufficient modularization as the class appears to have appropriate size and complexity for its functionality.
A3621: javaparser | B3621: com.github.javaparser.ast.validator.postprocessors.Java10PostProcessor | D3621: class | E3621: com.github.javaparser.ast.validator.postprocessors.Java10PostProcessor | F3621: 0 | G3621: The class has low complexity with only 3 methods (nom=3), 4 weighted method count (wmc=4), 29 lines of code (loc=29), and 2 public methods (nopm=2). The low method count, low cyclomatic complexity, and small size indicate sufficient modularization. The class appears to be appropriately decomposed for its functionality.
A3622: javaparser | B3622: com.github.javaparser.ast.validator.postprocessors.Java11PostProcessor | D3622: class | E3622: com.github.javaparser.ast.validator.postprocessors.Java11PostProcessor | F3622: 0 | G3622: The class has very low complexity with only 5 lines of code (loc=5), no methods (nom=0, nopm=0), no fields (nof=0, nopf=0), and minimal structural complexity (wmc=0, nc=1, dit=2). The low size and complexity indicate it is already sufficiently modularized and does not require further decomposition.
A3623: javaparser | B3623: com.github.javaparser.ast.validator.postprocessors.Java12PostProcessor | D3623: class | E3623: com.github.javaparser.ast.validator.postprocessors.Java12PostProcessor | F3623: 0 | G3623: The class has very low complexity with only 5 lines of code (loc=5), no methods (nom=0, nopm=0), no fields (nof=0, nopf=0), and minimal structural complexity (wmc=0, dit=3). The low size and complexity metrics indicate that further decomposition would not provide meaningful benefits for reducing size or implementation complexity.
A3624: javaparser | B3624: com.github.javaparser.ast.validator.postprocessors.Java13PostProcessor | D3624: class | E3624: com.github.javaparser.ast.validator.postprocessors.Java13PostProcessor | F3624: 0 | G3624: The class has very low complexity with only 5 lines of code (loc), no methods (nom=0, nopm=0), no fields (nof=0, nopf=0), and minimal structural complexity (wmc=0, nc=1). The low size and complexity metrics indicate that further decomposition would not provide meaningful benefits, and the class appears to be sufficiently modularized for its current scope.
A3625: javaparser | B3625: com.github.javaparser.ast.validator.postprocessors.Java14PostProcessor | D3625: class | E3625: com.github.javaparser.ast.validator.postprocessors.Java14PostProcessor | F3625: 0 | G3625: The class has very low complexity with only 5 lines of code (loc), no methods (nom=0), no fields (nof=0), and minimal structural complexity (wmc=0, dit=5). The low size and complexity indicate sufficient modularization for this class's current functionality.
A3626: javaparser | B3626: com.github.javaparser.ast.validator.postprocessors.Java15PostProcessor | D3626: class | E3626: com.github.javaparser.ast.validator.postprocessors.Java15PostProcessor | F3626: 0 | G3626: The class has very low complexity with only 5 lines of code (loc), no fields (nof=0), no methods (nom=0), and minimal structural complexity (wmc=0, dit=6). The lack of sufficient elements and complexity indicates that further decomposition is not warranted, as there is insufficient functionality to modularize.
A3627: javaparser | B3627: com.github.javaparser.ast.validator.postprocessors.Java16PostProcessor | C3627: insufficient_modularization | D3627: class | E3627: Java16PostProcessor | G3627: ```json_x000D_ {_x000D_ "class": com.github.javaparser.ast.validator.postprocessors.Java16PostProcessor,_x000D_ "detection": false,_x000D_ "justification": "The class has very low complexity with only 5 lines of code, no methods (nom=0, nopm=0), no fields (nof=0, nopf=0), and minimal structural complexity (wmc=0, dit=7). The lack of sufficient elements and complexity indicates that further decomposition is not warranted, as there is insufficient functionality to modularize."_x000D_ }_x000D_ ```
A3628: javaparser | B3628: com.github.javaparser.ast.validator.postprocessors.Java17PostProcessor | D3628: class | E3628: com.github.javaparser.ast.validator.postprocessors.Java17PostProcessor | F3628: 0 | G3628: The class has very low complexity with only 5 lines of code, no methods (nom=0, nopm=0), no fields (nof=0, nopf=0), and no dependencies. The low WMC (0), DIT (8), and simple structure indicate it is already well modularized. There is no evidence of insufficient modularization as the class appears to be appropriately simple and focused.
A3629: javaparser | B3629: com.github.javaparser.ast.validator.postprocessors.Java18PostProcessor | D3629: class | E3629: com.github.javaparser.ast.validator.postprocessors.Java18PostProcessor | F3629: 0 | G3629: The class has very low complexity with only 5 lines of code (loc), no methods (nom=0), no fields (nof=0), and no dependencies. The low WMC (0) and simple structure indicate it is already well modularized. There is no evidence of insufficient modularization as the class appears to be appropriately simple and focused.
A3630: javaparser | B3630: com.github.javaparser.ast.validator.postprocessors.Java19PostProcessor | D3630: class | E3630: com.github.javaparser.ast.validator.postprocessors.Java19PostProcessor | F3630: 0 | G3630: The class has very low complexity metrics (loc=5, wmc=0, nof=0, nom=0) and no dependencies, indicating it is already well-decomposed and does not exhibit insufficient modularization. The class appears to be a simple, focused implementation with minimal functionality that does not require further decomposition.
A3631: javaparser | B3631: com.github.javaparser.ast.validator.postprocessors.Java20PostProcessor | D3631: class | E3631: com.github.javaparser.ast.validator.postprocessors.Java20PostProcessor | F3631: 0 | G3631: The class has very low complexity with only 5 lines of code (loc), no methods (nom=0), no fields (nof=0), and minimal structural complexity (wmc=0, dit=11 but this is inheritance depth not complexity). The class appears to be a simple, focused component with minimal implementation complexity that does not require further decomposition.
A3632: javaparser | B3632: com.github.javaparser.ast.validator.postprocessors.Java21PostProcessor | D3632: class | E3632: com.github.javaparser.ast.validator.postprocessors.Java21PostProcessor | F3632: 0 | G3632: The class has very low complexity with only 5 lines of code (loc=5), no methods (nom=0, nopm=0), no fields (nof=0, nopf=0), and minimal structural complexity (wmc=0, nc=1). The depth of inheritance tree is 12 (dit=12) which indicates it inherits from a deep hierarchy, but this is not indicative of insufficient modularization within this class itself. With such minimal content and complexity, there is no evidence of insufficient modularization that would require further decomposition.
A3633: javaparser | B3633: com.github.javaparser.ast.validator.postprocessors.Java22PostProcessor | D3633: class | E3633: com.github.javaparser.ast.validator.postprocessors.Java22PostProcessor | F3633: 0 | G3633: The class has very low complexity with only 5 lines of code (loc), no methods (nom=0), no fields (nof=0), and minimal structural complexity (wmc=0, dit=13 but this is inheritance depth not complexity, nc=1). The class appears to be a simple, lightweight class that does not exhibit signs of insufficient modularization as it is already highly decomposed or serves a very specific minimal purpose.
A3634: javaparser | B3634: com.github.javaparser.ast.validator.postprocessors.Java23PostProcessor | D3634: class | E3634: com.github.javaparser.ast.validator.postprocessors.Java23PostProcessor | F3634: 0 | G3634: The class has very low complexity with 0 methods (nom=0), 0 fields (nof=0), and only 5 lines of code (loc=5). The WMC (Weighted Methods per Class) is 0, indicating no computational complexity. With no methods or fields, there is no meaningful decomposition possible, and the class is already at minimal size and complexity. The DIT of 14 indicates inheritance depth but does not indicate insufficient modularization in this case.
A3635: javaparser | B3635: com.github.javaparser.ast.validator.postprocessors.Java24PostProcessor | C3635: insufficient_modularization | D3635: class | E3635: Java24PostProcessor | G3635: ```json_x000D_ {_x000D_ "class": com.github.javaparser.ast.validator.postprocessors.Java24PostProcessor,_x000D_ "detection": false,_x000D_ "justification": "The class has very low complexity with only 5 lines of code (loc), no methods (nom=0), no fields (nof=0), and minimal structural complexity (wmc=0). The depth of inheritance tree (dit=15) indicates it inherits from a deep hierarchy but this alone does not indicate insufficient modularization. With such minimal content and no signs of high complexity or large size, there is no evidence of insufficient modularization requiring further decomposition."_x000D_ }_x000D_ ```
A3636: javaparser | B3636: com.github.javaparser.ast.validator.postprocessors.Java25PostProcessor | D3636: class | E3636: com.github.javaparser.ast.validator.postprocessors.Java25PostProcessor | F3636: 0 | G3636: The class has very low complexity with only 5 lines of code (loc), no methods (nom=0), no fields (nof=0), and minimal structural complexity (wmc=0). The depth of inheritance tree (dit=16) indicates it inherits from a deep hierarchy but this alone does not indicate insufficient modularization. With such minimal content and no signs of high complexity or large size, there is no evidence of insufficient modularization requiring further decomposition.
A3637: javaparser | B3637: com.github.javaparser.ast.validator.postprocessors.PostProcessors | D3637: class | E3637: com.github.javaparser.ast.validator.postprocessors.PostProcessors | F3637: 0 | G3637: The class has only 6 methods (nom=6) and 30 lines of code (loc=30), which indicates a relatively small and manageable size. The weighted method count (wmc=7) is low, suggesting low complexity. With only 1 field (nof=1) and 0 private fields (nopf=0), the class is not data-heavy. The lack of inheritance (dit=0) and low coupling (fanin=0, fanout=0) suggest simple relationships. While the class has some responsibilities related to post-processing, its small size and low complexity do not indicate insufficient modularization.
A3638: javaparser | B3638: com.github.javaparser.ast.validator.ProblemReporter | D3638: class | E3638: com.github.javaparser.ast.validator.ProblemReporter | F3638: 0 | G3638: The class has low complexity with only 4 methods (nom=4, wmc=4), 28 lines of code (loc=28), and 1 field (nof=1). The LCOM value of 0.75 indicates reasonable cohesion. With only 4 public methods and no private methods (nopm=4, nopf=0), the class is already well-decomposed and does not exhibit signs of insufficient modularization.
A3639: javaparser | B3639: com.github.javaparser.ast.validator.RecordAsTypeIdentifierNotAllowed | D3639: class | E3639: com.github.javaparser.ast.validator.RecordAsTypeIdentifierNotAllowed | F3639: 0 | G3639: The class has low complexity with only 4 methods (nom), 7 weighted method count (wmc), 28 lines of code (loc), and 1 field (nof). The low method count, low complexity metrics, and small size indicate sufficient modularization. LCOM value of 0.0 suggests good cohesion, and the class appears to be properly focused with a single responsibility.
A3640: javaparser | B3640: com.github.javaparser.ast.validator.ReservedKeywordValidator | D3640: class | E3640: com.github.javaparser.ast.validator.ReservedKeywordValidator | F3640: 0 | G3640: The class has low complexity metrics (WMC=5, LOC=23, NOM=3) and no inheritance depth issues (DIT=3 is reasonable). It has zero fan-in and fan-out dependencies, suggesting it's already well-decomposed. The LCOM value of 0.0 indicates good cohesion, and the small number of methods and fields suggest appropriate modularization.
A3641: javaparser | B3641: com.github.javaparser.ast.validator.SimpleValidator | D3641: class | E3641: com.github.javaparser.ast.validator.SimpleValidator | F3641: 0 | G3641: The class has only 1 method (nom=1, nopm=1), very low complexity (wmc=2), small size (loc=13), and no fields (nof=0, nopf=0). The low number of methods and minimal complexity indicate that further decomposition is not necessary as the class is already sufficiently simple and small.
A3642: javaparser | B3642: com.github.javaparser.ast.validator.SingleNodeTypeValidator | D3642: class | E3642: com.github.javaparser.ast.validator.SingleNodeTypeValidator | F3642: 0 | G3642: The class has low complexity with only 2 methods (nom=2), 2 public methods (nopm=2), 17 lines of code (loc=17), and low weighted method count (wmc=3). The lack of inheritance (dit=2) and low coupling (fanin=0, fanout=0) indicate proper modularization. The class appears to be well-focused with single responsibility.
A3643: javaparser | B3643: com.github.javaparser.ast.validator.TreeVisitorValidator | D3643: class | E3643: com.github.javaparser.ast.validator.TreeVisitorValidator | F3643: 0 | G3643: The class has only 2 methods (nom=2) and 15 lines of code (loc=15), which indicates a very small and focused class. The Weighted Method Count (wmc=3) is low, suggesting minimal complexity. With only 1 field (nof=1) and no class-level dependencies (fanin=0, fanout=0), this class appears to be well-decomposed and does not exhibit signs of insufficient modularization. The low LCOM value (0.0) indicates good cohesion within the class.
A3644: javaparser | B3644: com.github.javaparser.ast.validator.TypedValidator | D3644: class | E3644: com.github.javaparser.ast.validator.TypedValidator | F3644: 0 | G3644: The class has low complexity with only 3 methods (nom=3), 3 fields (nof=0 indicates no fields but nc=3 suggests 3 components), low WMC (3), and small size (18 LOC). The low number of methods and fields, combined with minimal complexity metrics, indicates sufficient modularization has been achieved.
A3645: javaparser | B3645: com.github.javaparser.ast.validator.Validator | D3645: class | E3645: com.github.javaparser.ast.validator.Validator | F3645: 0 | G3645: The class has low complexity with only 1 method (nom=1, wmc=1), 10 lines of code (loc=10), and 4 nested classes (nc=4). The low number of methods and low cyclomatic complexity indicate that the class is already well-decomposed and does not exhibit insufficient modularization. The nested classes suggest appropriate encapsulation rather than lack of decomposition.
A3646: javaparser | B3646: com.github.javaparser.ast.validator.Validators | D3646: class | E3646: com.github.javaparser.ast.validator.Validators | F3646: 0 | G3646: The class has low complexity with only 6 methods (nom=6, nopm=6), low weight method count (wmc=7), and reasonable lines of code (loc=30). The low LCOM value (0.0) indicates good cohesion, and the class appears to be well-focused with appropriate responsibilities. No clear indication of insufficient modularization based on the provided metrics.
A3647: javaparser | B3647: com.github.javaparser.ast.validator.VisitorValidator | D3647: class | E3647: com.github.javaparser.ast.validator.VisitorValidator | F3647: 0 | G3647: The class has low complexity with only 1 method (nom=1, nopm=1), low lines of code (loc=8), low number of classes (nc=6), and low weighted method count (wmc=1). The class appears to be sufficiently modularized with minimal functionality that does not warrant further decomposition.
... A5413: zxing | B5413: com.google.zxing.WriterException | D5413: class | E5413: com.google.zxing.WriterException | F5413: 0 | G5413: The class has only 3 methods (nom=3, nopm=3) and 14 lines of code (loc=14), which indicates a very small and simple class. With no fields (nof=0, nopf=0) and no dependencies (fanin=0, fanout=0), this appears to be a minimal exception class that is already well-decomposed. The low complexity (wmc=3) and small size do not suggest insufficient modularization.
